Workbook

Sheet summary
A1: BOQ FOR PROPOSED CIVIL & STRUCTURAL WORKS For SUYOG ELECTRICAL LTD. NO 245/33/B, 245/55/B/2, MOJE BODIDARA, TA.VADODARA, GUJARAT, INDIA.
A3: SR NO | B3: SECTION | C3: TITLE | D3: VIKRAM BUILDER | E3: TCC PROJECTS | F3: MAHAVIR CONSTRUCTION
D4: GRAND TOTAL | E4: GRAND TOTAL | F4: GRAND TOTAL
A5: 1 | B5: SECTION : -A | C5: EARTH WORK-SOLING | D5: =BOQ!F43 -> 16486314 | E5: =BOQ!H43 -> 15153396 | F5: =BOQ!J43 -> 18655311
A6: =A5+1 -> 2 | B6: SECTION : -B | C6: CONCRETE AND ALLIED WORK | D6: =BOQ!F127 -> 32102030 | E6: =BOQ!H127 -> 31604081 | F6: =BOQ!J127 -> 33191678
A7: =A6+1 -> 3 | B7: SECTION : -C | C7: MASONARY WORKS | D7: =BOQ!F155 -> 3686641.2 | E7: =BOQ!H155 -> 3904326 | F7: =BOQ!J155 -> 3877929.3
A8: =A7+1 -> 4 | B8: SECTION : -D | C8: FLOORING AND FACIAS. | D8: =BOQ!F214 -> 15539867 | E8: =BOQ!H214 -> 15982748 | F8: =BOQ!J214 -> 17835515
A9: =A8+1 -> 5 | B9: SECTION : -E | C9: PLASTERING , PAINTING , FINISHING | D9: =BOQ!F236 -> 6845605 | E9: =BOQ!H236 -> 7486265 | F9: =BOQ!J236 -> 7366271.1
A10: =A9+1 -> 6 | B10: SECTION : -F | C10: DOORS, WINDOWS AND VENTILATORS | D10: =BOQ!F318 -> 3848426.2 | E10: =BOQ!H318 -> 4262525 | F10: =BOQ!J318 -> 4363147.3
A11: =A10+1 -> 7 | B11: SECTION : -G | C11: STRCUTURAL STEEL WORK | D11: =BOQ!F334 -> 1766069 | E11: =BOQ!H334 -> 2344906.7 | F11: =BOQ!J334 -> 1879476.9
A12: =A11+1 -> 8 | B12: SECTION : -H | C12: ROOFING WORK
A13: =A12+1 -> 9 | B13: SECTION : -I | C13: WATERPROOFING | D13: =BOQ!F355 -> 830167 | E13: =BOQ!H355 -> 568914 | F13: =BOQ!J355 -> 990008.25
A14: =A13+1 -> 10 | B14: SECTION : -J | C14: MISCELLENOUS ITEMS | D14: =BOQ!F425 -> 3179626.2 | E14: =BOQ!H425 -> 2550960 | F14: =BOQ!J425 -> 2756781
A15: =A14+1 -> 11 | B15: SECTION : - K | C15: ROAD & PAVOR | D15: =BOQ!F490 -> 7397626.2 | E15: =BOQ!H490 -> 7172790 | F15: =BOQ!J490 -> 8919361.7
A16: =A15+1 -> 12 | B16: SECTION : - L | C16: PRE-CAST STORM WATER DRAIN
A17: TOTAL AMOUNT OF TENDER ITEMS | D17: =SUM(D5:D16) -> 91682372 | E17: =SUM(E5:E16) -> 91030911 | F17: =SUM(F5:F16) -> 99835480
C19: Percentange Respect to L 1 for Diffrence
C20: L 1 Compare to L 2 | D20: =100%-(($E$17/D17)) -> 0.0071056299
C21: L 1 Compare to L 3 | D21: =100%-(($E$17/F17)) -> 0.088190782

Sheet BOQ
A3: #VALUE!
A5: Sr. No. | B5: Description | C5: QTY. | D5: UNIT | E5: Vikram Builders | G5: TCC Projects | I5: Mahavir Construction
E6: RATE | F6: GRAND TOTAL | G6: RATE | H6: GRAND TOTAL | I6: RATE | J6: GRAND TOTAL
B7: SECTION- A EARTH WORK AND SOLING
A8: A-01 | B8: Cleaning the area by grass cutting, removing vegetations,roots of trees if any, scraping the existing surfaces up to 150mm, removal of all loose materials and other matters, etc. and disposing off the debris beyond the plant boundary as directed by the Engineer. | C8: QRO | D8: SQ.M. | E8: 23.75 | G8: 13 | I8: 13.825
A9: A-01A | B9: Clearing the area by jungle cutting, removing trees / bushes if any from roots, scraping the existing surfaces up to 150mm, removal of all loose materials and other matters, etc. and disposing off the debris beyond the plant boundary as directed by EIC. | C9: QRO | D9: SQ.M. | E9: 76 | G9: 66 | I9: 49.375
A10: A-02 | B10: Earth work excavation for all type of work in all soils like black cotton soil, clay, sand, soft and hard murrum, etc. but other than soft and hard rock including shoring, strutting and dewatering due to any sub soil water, rain water or any reason if required and refilling in foundations with selected excavated earth in 350mm layers, watering and consolidating to 250mm thickness, disposing off surplus excavated materials within the plant boundary at selected places, spreading evenly, leveling, etc. complete as per specifications and as directed. (Payment shall be made for 300mm from R.C.C. face for foundations and 200mm from R.C.C. face for GB) | C10: 0 | E10: 0 | G10: 0 | I10: 0 | J10: =I10*G9 -> 0
B11: a) From average ground level up to 1.50M depth. | C11: 3425 | D11: CUM | E11: 180.5 | F11: =E11*C11 -> 618212.5 | G11: 134 | H11: =IFERROR(G11*C11,"") -> 458950 | I11: 132.325 | J11: =$I11*$C11 -> 453213.12
B12: b) Below 1.5M up to 3M depth | C12: 600 | D12: CUM | E12: 190 | F12: =E12*C12 -> 114000 | G12: 150 | H12: =IFERROR(G12*C12,"") -> 90000 | I12: 145.1625 | J12: =$I12*$C12 -> 87097.5
B13: c) Below 3.0M up to 4.5M depth | C13: 226 | D13: CUM | E13: 256.5 | F13: =E13*C13 -> 57969 | G13: 160 | H13: =IFERROR(G13*C13,"") -> 36160 | I13: 157.0125 | J13: =$I13*$C13 -> 35484.825
B14: d) Below 4.5M up to 6.0M depth | C14: QRO | D14: CUM | E14: 318.25 | G14: 185 | H14: =IFERROR(G14*C14,"") | I14: 182.6875
B15: e) Below 6.0M up to 7.5M depth | C15: QRO | D15: CUM | E15: 389.5 | G15: 201 | H15: =IFERROR(G15*C15,"") | I15: 197.5
A16: A-03 | B16: Filling in plinth & foundation pits with approved materials including spreading in 150mm layers, watering, ramming, compacting with 10MT vibro/static roller or portable compactor wherever applicable as decided by the Engineer, leveling, etc. complete. (Measurements for compacted volume is considered) | C16: 0 | G16: 0 | H16: =IFERROR(G16*C16,"") -> 0
B17: a) With selected earth brought from outside | C17: 4450 | D17: CUM | E17: 413.25 | F17: =E17*C17 -> 1838962.5 | G17: 413 | H17: =IFERROR(G17*C17,"") -> 1837850 | I17: 402.9 | J17: =$I17*$C17 -> 1792905
B18: b) With approved filling sand brought from Outside. | C18: 2995 | D18: CUM | E18: 1268.25 | F18: =E18*C18 -> 3798408.8 | G18: 755 | H18: =IFERROR(G18*C18,"") -> 2261225 | I18: 1463.475 | J18: =$I18*$C18 -> 4383107.6
B19: c) Approved quarry dust filling | C19: QRO | D19: CUM | E19: 1391.75 | G19: 1031 | H19: =IFERROR(G19*C19,"") | I19: 987.5
A20: A-04 | B20: Disposing off surplus excavated materials by carting away, outside of company premises at location decided by contractor and shall be responsibility of contractor | C20: 365 | D20: CUM | E20: 261.25 | F20: =E20*C20 -> 95356.25 | G20: 197 | H20: =IFERROR(G20*C20,"") -> 71905 | I20: 188.6125 | J20: =$I20*$C20 -> 68843.562
A21: A-04A | B21: Disposing off dumped Earth / Debris by carting away, outside of company premises at location decided by contractor and shall be responsibility of contractor | C21: 0 | E21: 0 | F21: =E21*C21 -> 0 | G21: 0 | H21: =IFERROR(G21*C21,"") -> 0 | I21: 0 | J21: =I21*G20 -> 0
B22: a) Measurement of available material by volume | C22: 950 | D22: CUM | E22: 261.25 | F22: =E22*C22 -> 248187.5 | G22: 195 | H22: =IFERROR(G22*C22,"") -> 185250 | I22: 188.6125 | J22: =$I22*$C22 -> 179181.88
B23: b) Measurement of available material by Dumper | C23: QRO | D23: Nos. | E23: 2042.5 | G23: 955 | H23: =IFERROR(G23*C23,"") | I23: 1481.25
A24: A-05 | B24: Providing and laying black trap rubble soling at required level and grade in foundations, in plinth, ramps, etc. including hand packing, filling interstices with quarry / sand, watering and compacting with suitable vibro roller/ Static roller or earth compactor wherever applicable as decided by the Engineer to the consolidated thickness as stated below: | C24: 0 | E24: 0 | F24: =E24*C24 -> 0 | G24: 0 | H24: =IFERROR(G24*C24,"") -> 0 | I24: 0 | J24: =I24*G23 -> 0
B25: i) 230mm thick Soling | C25: QRO | D25: SQ.M | E25: 498.75 | G25: 519 | H25: =IFERROR(G25*C25,"") | I25: 592.5
B26: ii) 150mm thick compacted layer metal packing using 63-90 mm size hand broken stone etc. as directed Engineer in charge/consultant. | C26: 16475 | D26: SQ.M | E26: 266 | F26: =E26*C26 -> 4382350 | G26: 295 | H26: =IFERROR(G26*C26,"") -> 4860125 | I26: 339.7 | J26: =$I26*$C26 -> 5596557.5
B27: iii) 75mm thick compacted layer metal packing using 40-63 mm size hand broken stone etc. as directed Engineer in charge/consultant. | C27: 14882 | D27: SQ.M | E27: 147.25 | F27: =E27*C27 -> 2191374.5 | G27: 168 | H27: =IFERROR(G27*C27,"") -> 2500176 | I27: 172.8125 | J27: =$I27*$C27 -> 2571795.6
A28: A-06 | B28: Auguring(Upto 9m depth) of under ream pile foundation work in all sorts of soil viz. sand, clay, soft & hard murrum for execution of the above work. Contractor has to brought all necessary tools, tackles, equipments, manpower & supervision. Items also include carting of debris/soil, unloading, stacking, use of bentonite, spreading, levelling, compacting, consolidating surplus marterial within company premises, dewatering & one bulb as per design etc. complete as directed | C28: 0 | E28: 0 | F28: =E28*C28 -> 0 | G28: 0 | H28: =IFERROR(G28*C28,"") -> 0 | I28: 0 | J28: =I28*G27 -> 0
B29: (a) For 250mm dia. Pile | C29: QRO | D29: RM | E29: 237.5 | G29: 312 | H29: =IFERROR(G29*C29,"") | I29: 251.8125
B30: (b) For 300mm dia. Pile | C30: 40 | D30: RM | E30: 270.75 | F30: =E30*C30 -> 10830 | G30: 332 | H30: =IFERROR(G30*C30,"") -> 13280 | I30: 315.0125 | J30: =$I30*$C30 -> 12600.5
B31: (c) For 350mm dia. Pile | C31: 3936 | D31: RM | E31: 342 | F31: =E31*C31 -> 1346112 | G31: 382 | H31: =IFERROR(G31*C31,"") -> 1503552 | I31: 472.025 | J31: =$I31*$C31 -> 1857890.4
B32: (d) For 400mm dia. Pile | C32: 334 | D32: RM | E32: 522.5 | F32: =E32*C32 -> 174515 | G32: 436 | H32: =IFERROR(G32*C32,"") -> 145624 | I32: 535.225 | J32: =$I32*$C32 -> 178765.15
B33: (e) For 450mm dia. Pile | C33: 766 | D33: RM | E33: 570 | F33: =E33*C33 -> 436620 | G33: 519 | H33: =IFERROR(G33*C33,"") -> 397554 | I33: 597.4375 | J33: =$I33*$C33 -> 457637.12
B34: (f) For 500mm dia. Pile | C34: QRO | D34: RM | E34: 731.5 | G34: 727 | H34: =IFERROR(G34*C34,"") | I34: 660.6375
A35: A-06 a | B35: Auguring (Upto 12 m depth) of under ream pile foundation work in all sorts of soil viz. sand, clay, soft & hard murrum for execution of the above work. Contractor has to brought all necessary tools, tackles, equipments, manpower & supervision. Items also include carting of debris/soil, unloading, stacking, use of bentonite, spreading, levelling, compacting, consolidating surplus marterial within company premises, dewatering & one bulb as per design etc. complete as directed | E35: 0 | F35: =E35*C35 -> 0 | G35: 0 | H35: =IFERROR(G35*C35,"") -> 0 | I35: 0 | J35: =I35*G34 -> 0
B36: (a) For 400mm dia. Pile | C36: 1492 | D36: RM | E36: 617.5 | F36: =E36*C36 -> 921310 | G36: 435 | H36: =IFERROR(G36*C36,"") -> 649020 | I36: 535.225 | J36: =$I36*$C36 -> 798555.7
B37: (b) For 500mm dia. Pile | C37: 275 | D37: RM | E37: 916.75 | F37: =E37*C37 -> 252106.25 | G37: 519 | H37: =IFERROR(G37*C37,"") -> 142725 | I37: 660.6375 | J37: =$I37*$C37 -> 181675.31
A38: A-07 | B38: -do- as per item no. A-06 but for construction of extra bulb in the pile at any level. The size of the bulb will be as per design. | C38: 0 | E38: 0 | F38: =E38*C38 -> 0 | G38: 0 | H38: =IFERROR(G38*C38,"") -> 0 | I38: 0 | J38: =I38*G37 -> 0
B39: (a) For 250mm dia. Pile | C39: QRO | D39: NO | E39: 237.5 | G39: 307 | H39: =IFERROR(G39*C39,"") | I39: 296.25
B40: (b) For 300mm dia. Pile | C40: QRO | D40: NO | E40: 237.5 | G40: 316 | H40: =IFERROR(G40*C40,"") | I40: 395
B41: (c) For 350mm dia. Pile | C41: QRO | D41: NO | E41: 332.5 | G41: 378 | H41: =IFERROR(G41*C41,"") | I41: 493.75
B42: (d) For 400mm dia. Pile | C42: QRO | D42: NO | E42: 380 | G42: 408 | H42: =IFERROR(G42*C42,"") | I42: 691.25
B43: TOTAL OF SECTION `A` | C43: 0 | E43: 0 | F43: =SUM(F8:F42) -> 16486314 | G43: 0 | H43: =SUM(H8:H42) -> 15153396 | J43: =SUM(J8:J42) -> 18655311
B44: SECTION - B CONCRETE | C44: 0 | E44: 0 | G44: 0
B45: Note : 1. Cement for site-mixed concrete will be under the contractor’s scope of supply. 2. Ready-Mix Cement (RMC) will be supplied by the client. 3. The contractor is responsible for maintaining accurate records of concrete usage. 4.The contractor must regularly coordinate with the Engineer-in-Charge to verify: 1.The quantity of RMC used. 2.The quantity of site-mixed concrete used. | E45: 0 | G45: 0 | H45: =IFERROR(G45*C45,"") -> 0 | I45: 0
B46: RMC Approved Vendor : Dev RMC , Vikram RMC | E46: 0 | G46: 0 | H46: =IFERROR(G46*C46,"") -> 0 | I46: 0
B47: Contractor with their own Batch Mix Plant at site of Min 20 CUM /Hour Capacity and Transit Mixers/concrete Pump for the Concrete works will be given preference. | E47: 0 | G47: 0 | H47: =IFERROR(G47*C47,"") -> 0 | I47: 0
B48: All major Concreting shall be done with concrete supplied from Batch Mix Plant installed at site or with concrete bought from Approved RMC plant. Only for small concreting (less than 5 M3),Contractor Shall have their own Weigh Batch Mixer of 5 Bag capacity or Self loading Ajex Mixer for the concrete work. Volumetric mixing for structural concreting will not allowed . | E48: 0 | G48: 0 | H48: =IFERROR(G48*C48,"") -> 0 | I48: 0
B49: Basic Rate of Cement ( OPC 53 ) : ( Contractor Scope ) : 282 Rs per Bag | E49: 0 | G49: 0 | H49: =IFERROR(G49*C49,"") -> 0 | I49: 0
A50: B-01 | B50: Providing and laying Plain cement concrete below all R.C.C. member, floors, ramps, chembers etc. with 20mm nominal size graded stone aggregates of approved quality (black trap only) including leveling, compacting, curing and form work if any, etc. complete. | C50: 0 | E50: 0 | G50: 0 | H50: =IFERROR(G50*C50,"") -> 0 | I50: 0
B51: a) Mix 1: 4: 8 | C51: 1407 | D51: CUM | E51: 4322.5 | F51: =E51*C51 -> 6081757.5 | G51: 3748 | H51: =IFERROR(G51*C51,"") -> 5273436 | I51: 4507.9375 | J51: =$I51*$C51 -> 6342668.1
B52: b) Mix 1: 3: 6 | C52: QRO | D52: CUM | E52: 4655 | G52: 4000 | H52: =IFERROR(G52*C52,"") | I52: 4834.8
A53: B-02 | B53: Providing and laying reinforced cement concrete with 20mm and down size graded stone aggregates in all types of concrete works such as footings, columns, pedestals, rafts, beams, lofts, slabs, walls, lintels, chajjas, canopies, facias, fins, bands, shelves, staircases, all other any type of structural members, pits, chambers, rain water chutes, gutters, pardi, curbs, pipe racks, & equipment foundations, etc. of square, rectangular, hexagonal, octagonal and circular shapes including leaving pockets, vatas, openings in slabs, including vibrating, tamping, finishing, curing and rendering if required, etc. complete as per drawings and specifications but excluding the cost of formwork and reinforcement. (No false staging shall be given.) | C53: 0 | E53: 0 | F53: =E53*C53 -> 0 | G53: 0 | H53: =IFERROR(G53*C53,"") -> 0 | I53: 0 | J53: =I53*G52 -> 0
B54: Scope of Cement Work on the Contractor’s Side | E54: 0 | G54: 0 | H54: =IFERROR(G54*C54,"") -> 0 | I54: 0
B55: a) M : 20 Grade (Min. Cement - 300 KG/M3) | C55: 0 | E55: 0 | F55: =E55*C55 -> 0 | G55: 0 | H55: =IFERROR(G55*C55,"") -> 0 | I55: 0 | J55: =I55*G53 -> 0
B56: 1. In foundations and up to plinths (FFL) at all depths: | C56: QRO | D56: CUM | E56: 5343.75 | G56: 4260 | H56: =IFERROR(G56*C56,"") | I56: 5826.25
B57: i) From FFL up to + 5.5 M lvl. | C57: QRO | D57: CUM | E57: 5628.75 | G57: 4571 | H57: =IFERROR(G57*C57,"") | I57: 5925
B58: b) M: 25 Grade (Min. Cement - 340 KG/M3) | C58: 0 | E58: 0 | F58: =E58*C58 -> 0 | G58: 0 | H58: =IFERROR(G58*C58,"") -> 0 | I58: 0 | J58: =I58*G57 -> 0
B59: 1. In foundations and up to plinths (FFL) at all depths: | C59: 884 | D59: CUM | E59: 5391.25 | F59: =E59*C59 -> 4765865 | G59: 5297 | H59: =IFERROR(G59*C59,"") -> 4682548 | I59: 6011.9 | J59: =$I59*$C59 -> 5314519.6
B60: i) From FFL up to + 4.5 M lvl. | C60: 329.5 | D60: CUM | E60: 5676.25 | F60: =E60*C60 -> 1870324.4 | G60: 5507 | H60: =IFERROR(G60*C60,"") -> 1814556.5 | I60: 6145.2125 | J60: =$I60*$C60 -> 2024847.5
B61: ii) Above 4.5M lvl up to + 8.0 M lvl | C61: 30 | D61: CUM | E61: 5961.25 | F61: =E61*C61 -> 178837.5 | G61: 5715 | H61: =IFERROR(G61*C61,"") -> 171450 | I61: 6178.7875 | J61: =$I61*$C61 -> 185363.62
B62: iii) Above 8.0M lvl up to + 11.5 M lvl | C62: 14 | D62: CUM | E62: 6531.25 | F62: =E62*C62 -> 91437.5 | G62: 5818 | H62: =IFERROR(G62*C62,"") -> 81452 | I62: 6279.5125 | J62: =$I62*$C62 -> 87913.175
B63: iv) Above 11.5M lvl up to + 17.5 M lvl | C63: 24 | D63: CUM | E63: 6816.25 | F63: =E63*C63 -> 163590 | G63: 5922 | H63: =IFERROR(G63*C63,"") -> 142128 | I63: 6279.5125 | J63: =$I63*$C63 -> 150708.3
B64: v) Above 17.5M lvl up to + 21.0 M lvl | C64: 7 | E64: 0 | F64: =E64*C64 -> 0 | G64: 6234 | H64: =IFERROR(G64*C64,"") -> 43638 | I64: 6345.675 | J64: =$I64*$C64 -> 44419.725
B65: c) Extra for M30 Concrete in place of M25 (Min. Cement- 370 KG/M3) | C65: QRO | D65: CUM | E65: 0 | G65: 321 | H65: =IFERROR(G65*C65,"") | I65: 493.75
A66: B-02A | B66: Ready Mix Concreate (Prior Permission shall be taken before using Ready Mix Concrete from engineer In-charge) | C66: 0 | E66: 0 | F66: =E66*C66 -> 0 | G66: 0 | H66: =IFERROR(G66*C66,"") -> 0 | I66: 0 | J66: =I66*G65 -> 0
B67: Providing and laying ready mix concrete with 20mm and down size graded stone aggregates Without flyash in all types of concrete works such as footings, columns, pedestals, rafts, beams, lofts, slabs, walls, lintels, chajjas, canopies, facias, fins, bands, shelves, staircases, pits, chambers, rain water chutes, gutt­ers, pardi, curbs, pipe racks, & equipment foundations, etc. of square, rectangular, hexagonal, octagonal and circular shapes including leaving pockets, openings in slabs, vibrating, tamping, finishing, curing and rendering if required, etc. complete as per drawings and specifications but excluding the cost of formwork and reinforcement. | C67: 0 | E67: 0 | F67: =E67*C67 -> 0 | G67: 0 | H67: =IFERROR(G67*C67,"") -> 0 | I67: 0 | J67: =I67*G66 -> 0
B68: Scope of Cement Work on the Client’s Side | E68: 0 | G68: 0 | H68: =IFERROR(G68*C68,"") -> 0 | I68: 0
A69: B-02 A 0 | B69: Providing and laying Plain cement concrete below all R.C.C. member, floors, ramps, chembers etc. with 20mm nominal size graded stone aggregates of approved quality (black trap only) including leveling, compacting, curing and form work if any, etc. complete. | E69: 0 | G69: 0 | H69: =IFERROR(G69*C69,"") -> 0 | I69: 0
B70: a) Mix 1: 4: 8 | E70: 3396.25 | G70: 3325 | H70: =IFERROR(G70*C70,"") -> 0 | I70: 3327.875
B71: b) Mix 1: 3: 6 | E71: 3372.5 | G71: 3325 | H71: =IFERROR(G71*C71,"") -> 0 | I71: 3327.875
A72: B-02 A1 | B72: In foundations and up to plinths (FFL) at all depths: | C72: 0 | E72: 0 | F72: =E72*C72 -> 0 | G72: 0 | H72: =IFERROR(G72*C72,"") -> 0 | I72: 0 | J72: =I72*G67 -> 0
B73: a) M: 20 Grade (min . Cement : 300 kg/m3) | C73: QRO | D73: Cu.m | E73: 3467.5 | G73: 38446 | H73: =IFERROR(G73*C73,"") | I73: 3473.0375
B74: b) M: 25 Grade (min . Cement : 340 kg/m3) | C74: 556 | D74: Cu.m | E74: 3467.5 | F74: =E74*C74 -> 1927930 | G74: 3844 | H74: =IFERROR(G74*C74,"") -> 2137264 | I74: 3477.975 | J74: =$I74*$C74 -> 1933754.1
B75: c) Extra for M30 Concrete in place of M25 (Min. Cement- 370 KG/M3) | C75: QRO | D75: Cu.m | E75: 0 | G75: 1454 | H75: =IFERROR(G75*C75,"") | I75: 289.3375
A76: B-02 A2 | B76: In superstructure above finished floor level at all heights. | E76: 0 | F76: =E76*C76 -> 0 | G76: 0 | H76: =IFERROR(G76*C76,"") -> 0 | I76: 0 | J76: =I76*G75 -> 0
B77: a) M : 20 Grade | E77: 0 | F77: =E77*C77 -> 0 | G77: 0 | H77: =IFERROR(G77*C77,"") -> 0 | I77: 0 | J77: =I77*G76 -> 0
B78: i) From FFL up to + 5.5M lvl. | C78: QRO | D78: Cu.m | E78: 3800 | G78: 3325 | H78: =IFERROR(G78*C78,"") | I78: 3367.375
B79: ii) Above + 5.5M lvl. | C79: QRO | D79: Cu.m | E79: 4085 | G79: 3740 | H79: =IFERROR(G79*C79,"") | I79: 3505.625
B80: b) M : 25 Grade | E80: 0 | F80: =E80*C80 -> 0 | G80: 0 | H80: =IFERROR(G80*C80,"") -> 0 | I80: 0 | J80: =I80*G79 -> 0
B81: i) From FFL up to + 4.5 M lvl. | C81: 100 | D81: Cu.m | E81: 3800 | F81: =E81*C81 -> 380000 | G81: 3740 | H81: =IFERROR(G81*C81,"") -> 374000 | I81: 3611.2875 | J81: =$I81*$C81 -> 361128.75
B82: ii) Above 4.5M lvl up to + 8.0 M lvl | C82: 100 | D82: Cu.m | E82: 4085 | F82: =E82*C82 -> 408500 | G82: 3740 | H82: =IFERROR(G82*C82,"") -> 374000 | I82: 3644.8625 | J82: =$I82*$C82 -> 364486.25
B83: iii) Above 8.0M lvl up to + 11.5 M lvl | C83: 135 | D83: Cu.m | E83: 4227.5 | F83: =E83*C83 -> 570712.5 | G83: 3844 | H83: =IFERROR(G83*C83,"") -> 518940 | I83: 3644.8625 | J83: =$I83*$C83 -> 492056.44
B84: iv) Above 11.5M lvl up to + 17.5 M lvl | C84: 170 | D84: Cu.m | E84: 4370 | F84: =E84*C84 -> 742900 | G84: 3948 | H84: =IFERROR(G84*C84,"") -> 671160 | I84: 3744.6 | J84: =$I84*$C84 -> 636582
B85: v) Above 17.5M lvl up to + 21.0 M lvl | C85: 50 | D85: Cu.m | E85: 4750 | F85: =E85*C85 -> 237500 | G85: 4260 | H85: =IFERROR(G85*C85,"") -> 213000 | I85: 3811.75 | J85: =$I85*$C85 -> 190587.5
B86: c) Extra for M30 Concrete in place of M25 (Min. Cement- 370 KG/M3) | C86: 450 | D86: Cu.m | E86: 0 | F86: =E86*C86 -> 0 | G86: 519 | H86: =IFERROR(G86*C86,"") -> 233550 | I86: 277.4875 | J86: =$I86*$C86 -> 124869.38
A87: B-02B | B87: Providing and laying reinforced cement concrete with 20mm and down size graded stone aggregates in PILE. of circular shapes including tamping, curing and development of pile- including use of trimi, breaking (Upto 0.60m length), cleanning etc. complete as per drawings and specifications but excluding the cost of formwork and reinforcement. (USE GRADE OF CONC. M25) | C87: 0 | E87: 0 | F87: =E87*C87 -> 0 | G87: 0 | H87: =IFERROR(G87*C87,"") -> 0 | I87: 0 | J87: =I87*G86 -> 0
B88: (a) For Pile | C88: 1028 | D88: CUM | E88: 3576.75 | F88: =E88*C88 -> 3676899 | G88: 3323 | H88: =IFERROR(G88*C88,"") -> 3416044 | I88: 3416.75 | J88: =$I88*$C88 -> 3512419
A89: B-02C | B89: Providing and laying reinforced cement concrete with 20mm and down size graded stone aggregates in PRECAST concrete works for storm water trench, Chamber Cover etc. of square, rectangular, hexagonal, octagonal and circular shapes including leaving pockets, openings in covers, vibrating, tamping, finishing, curing and rendering if required, etc. complete as per drawings and specifications. The rate includes the cost of formwork and installing the elements in line and level. (Reinforcement steel is paid seperately in item no. B-05 ) | C89: 0 | E89: 0 | F89: =E89*C89 -> 0 | G89: 0 | H89: =IFERROR(G89*C89,"") -> 0 | I89: 0 | J89: =I89*G88 -> 0
B90: (a) M25 grade | C90: QRO | D90: CUM | E90: 13490 | G90: 9040 | H90: =IFERROR(G90*C90,"") | I90: 8393.75
B91: (b) M30 grade | C91: QRO | D91: CUM | E91: 13775 | G91: 10391 | H91: =IFERROR(G91*C91,"") | I91: 9875
A92: B-02D | B92: Providing and laying M25 Grade Reinforced cement concrete for water retaining structures/Cable Trech / basement structures/over head tanks, ETP, scale pit, basins sumps / sump pits, manholes, inspection chambers of sewage / drainage lines etc at any level and location. Including addition of water proofing compound WAREP 1000L Manufactured by Thermax Ltd. , FOSROC-CONPLAST '-X4211C- or equivalent approved make in concrete as per approved manufacturer's specification, including pressure cement grouting of mix 1:1 with water proofing additives MAXGROUT 100 MANUFACTURED by THERMAX LTD.or equivalent at construction joints, weak spot / honey combs and testing the same for water tightness as per requirements of IS 3370 and making good defects / leakages as instructed by Engineers / Owners. Rate also to include cost of water proofing compound, testing and rectification of leakage etc | C92: 0 | E92: 0 | F92: =E92*C92 -> 0 | G92: 0 | H92: =IFERROR(G92*C92,"") -> 0 | I92: 0 | J92: =I92*G91 -> 0
B93: Scope of Cement Work – Client’s Responsibility The contractor shall include the cost of waterproofing chemicals separately in the quotation, as this will be considered an additional item beyond the standard cement work. | E93: 0 | G93: 0 | H93: =IFERROR(G93*C93,"") -> 0 | I93: 0
B94: a) M: 25 Grade (Minimum Cement : 340 kg/M3) | C94: 0 | E94: 0 | F94: =E94*C94 -> 0 | G94: 0 | H94: =IFERROR(G94*C94,"") -> 0 | I94: 0 | J94: =I94*G92 -> 0
B95: 1. In foundations and up to plinths (FFL) at all depths: | C95: QRO | D95: CUM | E95: 5082.5 | G95: 3844 | H95: =IFERROR(G95*C95,"") | I95: 3851.25
B96: i) From FFL up to +4.5 M lvl. | C96: QRO | D96: CUM | E96: 5225 | G96: 3844 | H96: =IFERROR(G96*C96,"") | I96: 3950
B97: ii) Above + 4.5M lvl up to + 8.00 M lvl | C97: QRO | D97: CUM | E97: 5462.5 | G97: 3948 | H97: =IFERROR(G97*C97,"") | I97: 4048.75
B98: iii) Above + 8.0 M lvl up to + 11.50 M lvl | C98: QRO | D98: CUM | E98: 5700 | G98: 4156 | H98: =IFERROR(G98*C98,"") | I98: 4246.25
B99: iv) Above +11.5 M lvl up to + 17.50 M lvl | C99: QRO | D99: CUM | E99: 5890 | G99: 4260 | H99: =IFERROR(G99*C99,"") | I99: 4443.75
B100: ii) Above + 17.5M lvl up to + 21.0M lvl | C100: QRO | D100: CUM | E100: 6270 | G100: 4364 | H100: =IFERROR(G100*C100,"") | I100: 4641.25
A101: B-03 | B101: For addition of approved quality plasticiser as directed and specified by the engineer incharge (asian or SIKA make only) | C101: 0 | E101: 0 | G101: 0 | H101: =IFERROR(G101*C101,"") -> 0 | I101: 0
B102: a) For early de shuttering (basic rate:90 Rs/Ltr.) | C102: QRO | D102: LTRS | E102: 114 | G102: 94 | H102: =IFERROR(G102*C102,"") | I102: 123.4375
A103: B-04 | B103: Collecting , fabricating, laying and fixing in position reinforcement for all type of RCC works at all levels, including cost of straightening, cutting, bending to required shape, binding with 16 gauge MS annealed binding wire, spacer blocks of cement mortar 1:2 with embedded binding wire of appropriate length, etc. complete as per drawings and specifications [Chairs, pins will not be measured and paid extra. Only authorized laps shall be measured and paid for] Note:- HYSD reinforcements (Fe500D) | C103: 0 | E103: 0 | F103: =E103*C103 -> 0 | G103: 0 | H103: =IFERROR(G103*C103,"") -> 0 | I103: 0 | J103: =I103*G102 -> 0
...

Sheet BOQ-CCV 
B1: ESTIMATED BOQ FOR PROPOSED CIVIL & STRUCTURAL WORKS For SUYOG ELECTRICAL LTD. NO 245/33/B,245/55/B/2,MOJE BODIDARA, TA.VADODARA, GUJARAT, INDIA.
A2: Followings are the scope of work: - Shed building Civil and Structural works (Excluding PEB shed) - Approximately 1250 sqm area (G+3) FLOOR
A4: BOQ
A5: Sr. No. | B5: Description | C5: QTY. | D5: UNIT | E5: RATE | F5: AMOUNT
B6: SECTION- A EARTH WORK AND SOLING
A7: A-01 | B7: Cleaning the area by grass cutting, removing vegetations,roots of trees if any, scraping the existing surfaces up to 150mm, removal of all loose materials and other matters, etc. and disposing off the debris beyond the plant boundary as directed by the Engineer. | D7: SQ.M. | E7: 35 | F7: =E7*C7 -> 0
A8: A-01A | B8: Clearing the area by jungle cutting, removing trees / bushes if any from roots, scraping the existing surfaces up to 150mm, removal of all loose materials and other matters, etc. and disposing off the debris beyond the plant boundary as directed by EIC. | D8: SQ.M. | E8: 25 | F8: =E8*C8 -> 0
A9: A-02 | B9: Earth work excavation for all type of work in all soils like black cotton soil, clay, sand, soft and hard murrum, etc. but other than soft and hard rock including shoring, strutting and dewatering due to any sub soil water, rain water or any reason if required and refilling in foundations with selected excavated earth in 350mm layers, watering and consolidating to 250mm thickness, disposing off surplus excavated materials within the plant boundary at selected places, spreading evenly, leveling, etc. complete as per specifications and as directed. (Payment shall be made for 300mm from R.C.C. face for foundations and 200mm from R.C.C. face for GB)
B10: a) From average ground level up to 1.50M depth. | C10: 642 | D10: CUM | E10: 250 | F10: =E10*C10 -> 160500
B11: b) Below 1.5M up to 3M depth | D11: CUM | E11: 285 | F11: =E11*C11 -> 0
B12: c) Below 3.0M up to 4.5M depth | D12: CUM | E12: 350
B13: d) Below 4.5M up to 6.0M depth | D13: CUM | E13: 450
B14: e) Below 6.0M up to 7.5M depth | D14: CUM | E14: 575
A15: A-03 | B15: Filling in plinth & foundation pits with approved materials including spreading in 150mm layers, watering, ramming, compacting with 10MT vibro/static roller or portable compactor wherever applicable as decided by the Engineer, leveling, etc. complete. (Measurements for compacted volume is considered)
B16: a) With selected earth brought from outside | C16: 57 | D16: CUM | E16: 490 | F16: =E16*C16 -> 27930
B17: b) With approved filling sand brought from Outside. | C17: 57 | D17: CUM | E17: 1025 | F17: =E17*C17 -> 58425
B18: c) Approved quarry dust filling | D18: CUM | E18: 1150
A19: A-04 | B19: Disposing off surplus excavated materials by carting away, outside of company premises at location decided by contractor and shall be responsibility of contractor | D19: CUM | E19: 150 | F19: =E19*C19 -> 0
A20: A-04A | B20: Disposing off dumped Earth / Debris by carting away, outside of company premises at location decided by contractor and shall be responsibility of contractor
B21: a) Measurement of available material by volume | D21: CUM | E21: 100 | F21: =E21*C21 -> 0
B22: b) Measurement of available material by Dumper | D22: Nos. | E22: 3500
A23: A-05 | B23: Providing and laying black trap rubble soling at required level and grade in foundations, in plinth, ramps, etc. including hand packing, filling interstices with quarry / sand, watering and compacting with suitable vibro roller/ Static roller or earth compactor wherever applicable as decided by the Engineer to the consolidated thickness as stated below:
B24: i) 230mm thick Soling | D24: SQ.M | E24: 517
B25: ii) 150mm thick compacted layer metal packing using 63-90 mm size hand broken stone etc. as directed Engineer in charge/consultant. | C25: 284 | D25: SQ.M | E25: 310 | F25: =E25*C25 -> 88040
B26: iii) 75mm thick compacted layer metal packing using 40-63 mm size hand broken stone etc. as directed Engineer in charge/consultant. | C26: 284 | D26: SQ.M | E26: 150 | F26: =E26*C26 -> 42600
A27: A-06 | B27: Auguring(Upto 11m depth) of under ream pile foundation work in all sorts of soil viz. sand, clay, soft & hard murrum for execution of the above work. Contractor has to brought all necessary tools, tackles, equipments, manpower & supervision. Items also include carting of debris/soil, unloading, stacking, use of bentonite, spreading, levelling, compacting, consolidating surplus marterial within company premises, dewatering & one bulb as per design etc. complete as directed
B28: (a) For 250mm dia. Pile | D28: RM | E28: 300
B29: (b) For 300mm dia. Pile | D29: RM | E29: 350 | F29: =E29*C29 -> 0
B30: (c) For 350mm dia. Pile | D30: RM | E30: 425 | F30: =E30*C30 -> 0
B31: (d) For 400mm dia. Pile | D31: RM | E31: 495 | F31: =E31*C31 -> 0
B32: (e) For 500mm dia. Pile | C32: 1834 | D32: RM | E32: 500 | F32: =E32*C32 -> 917000
A33: A-07 | B33: -do- as per item no. A-06 but for construction of extra bulb in the pile at any level. The size of the bulb will be as per design.
B34: (a) For 250mm dia. Pile | D34: NO | E34: 300
B35: (b) For 300mm dia. Pile | D35: NO | E35: 400
B36: (c) For 350mm dia. Pile | D36: NO | E36: 450
B37: (d) For 400mm dia. Pile | D37: NO | E37: 500
B38: TOTAL OF SECTION `A` | F38: =SUM(F7:F37) -> 1294495
B39: SECTION - B CONCRETE
A40: B-01 | B40: Providing and laying Plain cement concrete below all R.C.C. member, floors, ramps, chembers etc. with 20mm nominal size graded stone aggregates of approved quality (black trap only) including leveling, compacting, curing and form work if any, etc. complete.
B41: a) Mix 1: 4: 8 | C41: 60 | D41: CUM | E41: 4100 | F41: =E41*C41 -> 246000
B42: b) Mix 1: 3: 6 | D42: CUM | E42: 4175
A43: B-02 | B43: Providing and laying reinforced cement concrete with 20mm and down size graded stone aggregates in all types of concrete works such as footings, columns, pedestals, rafts, beams, lofts, slabs, walls, lintels, chajjas, canopies, facias, fins, bands, shelves, staircases, all other any type of structural members, pits, chambers, rain water chutes, gutters, pardi, curbs, pipe racks, & equipment foundations, etc. of square, rectangular, hexagonal, octagonal and circular shapes including leaving pockets, vatas, openings in slabs, including vibrating, tamping, finishing, curing and rendering if required, etc. complete as per drawings and specifications but excluding the cost of formwork and reinforcement. (No false staging shall be given.) Cement Make: Ultratech / JK Lakshmi / Ambuja - OPC 53 grade (Applicable to all items)
B44: a) M : 20 Grade (Min. Cement - 300 KG/M3)
B45: 1. In foundations and up to plinths (FFL) at all depths: | D45: CUM | E45: 5450
B46: i) From FFL up to + 5.5 M lvl. | D46: CUM | E46: 5950
B47: b) M: 25 Grade (Min. Cement - 340 KG/M3)
B48: 1. In foundations and up to plinths (FFL) at all depths: | C48: 270 | D48: CUM | E48: 5850 | F48: =E48*C48 -> 1579500
B49: i) From FFL up to + 5.0 M lvl. | C49: 134 | D49: CUM | E49: 6175 | F49: =E49*C49 -> 827450
B50: ii) Above + 5.0M lvl up to + 11.0 M lvl | C50: 128 | D50: CUM | E50: 6350 | F50: =E50*C50 -> 812800
B51: ii) Above + 11.0M lvl up to + 16.0 M lvl | C51: 149 | D51: CUM | E51: 6525 | F51: =E51*C51 -> 972225
B52: ii) Above + 16.0M lvl up to + 21.0 M lvl | C52: 211 | D52: CUM | E52: 6700 | F52: =E52*C52 -> 1413700
B53: c) Extra for M30 Concrete in place of M25 (Min. Cement- 370 KG/M3) | D53: CUM | E53: 950 | F53: =E53*C53 -> 0
A54: B-02A | B54: Ready Mix Concreate (Prior Permission shall be taken before using Ready Mix Concrete from engineer Incharge)
B55: Providing and laying ready mix concrete with 20mm and down size graded stone aggregates Without flyash in all types of concrete works such as footings, columns, pedestals, rafts, beams, lofts, slabs, walls, lintels, chajjas, canopies, facias, fins, bands, shelves, staircases, pits, chambers, rain water chutes, gutt­ers, pardi, curbs, pipe racks, & equipment foundations, etc. of square, rectangular, hexagonal, octagonal and circular shapes including leaving pockets, openings in slabs, vibrating, tamping, finishing, curing and rendering if required, etc. complete as per drawings and specifications but excluding the cost of formwork and reinforcement. Cement: OPC53 grade Ultra tech, Ambuja Supply of cement will be in contractor's scope. Mix Design has to be approved from Consultant.
A56: B-02 A1 | B56: In foundations and up to plinths (FFL) at all depths:
B57: a) M: 20 Grade (min . Cement : 300 kg/m3) | D57: Cu.m | E57: 5450
B58: b) M: 25 Grade (min . Cement : 340 kg/m3) | D58: Cu.m | E58: 5850 | F58: =E58*C58 -> 0
B59: c) Extra for M30 Concrete in place of M25 (Min. Cement- 370 KG/M3) | D59: Cu.m | E59: 950
A60: B-02 A2 | B60: In superstructure above finished floor level at all heights.
B61: a) M : 20 Grade
B62: i) From FFL up to + 5.5M lvl. | D62: Cu.m | E62: 5700 | F62: =E62*C62 -> 0
B63: ii) Above + 5.5M lvl. | D63: Cu.m
B64: b) M : 25 Grade
B65: i) From FFL up to + 5.5M lvl. | D65: Cu.m | E65: 5900 | F65: =E65*C65 -> 0
B66: ii) Above + 5.5M lvl up to + 11.0M lvl | D66: Cu.m | E66: 6650
B67: c) Extra for M30 Concrete in place of M25 (Min. Cement- 370 KG/M3) | D67: Cu.m | E67: 950
A68: B-02B | B68: Providing and laying reinforced cement concrete with 20mm and down size graded stone aggregates in PILE. of circular shapes including tamping, curing and development of pile- including use of trimi, breaking (Upto 0.60m length), cleanning etc. complete as per drawings and specifications but excluding the cost of formwork and reinforcement. (USE GRADE OF CONC. M25)
B69: (a) For 250mm dia. Pile | D69: CUM | E69: 5600
B70: (b) For 300mm dia. Pile | D70: CUM | E70: 5369 | F70: =E70*C70 -> 0
B71: (b) For 350mm dia. Pile | D71: CUM | E71: 5650 | F71: =E71*C71 -> 0
B72: (c) For 400mm dia. Pile | D72: CUM | E72: 5650 | F72: =E72*C72 -> 0
B73: (d) For 500mm dia. Pile | C73: 406 | D73: CUM | E73: 5650 | F73: =E73*C73 -> 2293900
A74: B-02C | B74: Providing and laying reinforced cement concrete with 20mm and down size graded stone aggregates in PRECAST concrete works for storm water trench, Chamber Cover etc. of square, rectangular, hexagonal, octagonal and circular shapes including leaving pockets, openings in covers, vibrating, tamping, finishing, curing and rendering if required, etc. complete as per drawings and specifications. The rate includes the cost of formwork and installing the elements in line and level. (Reinforcement steel is paid seperately in item no. B-05 )
B75: (a) M25 grade | D75: CUM | E75: 9500 | F75: =E75*C75 -> 0
B76: (b) M30 grade | D76: CUM | E76: 9500 | F76: =E76*C76 -> 0
A77: B-02D | B77: Providing and laying M25 Grade Reinforced cement concrete for water retaining structures/Cable Trech / basement structures/over head tanks, ETP, scale pit, basins sumps / sump pits, manholes, inspection chambers of sewage / drainage lines etc at any level and location. Including addition of water proofing compound WAREP 1000L Manufactured by Thermax Ltd. , FOSROC-CONPLAST '-X4211C- or equivalent approved make in concrete as per approved manufacturer's specification, including pressure cement grouting of mix 1:1 with water proofing additives MAXGROUT 100 MANUFACTURED by THERMAX LTD.or equivalent at construction joints, weak spot / honey combs and testing the same for water tightness as per requirements of IS 3370 and making good defects / leakages as instructed by Engineers / Owners. Rate also to include cost of water proofing compound, testing and rectification of leakage etc
B78: a) M: 25 Grade (Minimum Cement : 340 kg/M3)
B79: 1. In foundations and up to plinths (FFL) at all depths: | D79: CUM | E79: 5750 | F79: =E80*C79 -> 0
B80: i) From FFL up to + 5.5 M lvl. | D80: CUM | E80: 6650
B81: ii) Above + 5.5M lvl up to + 11.0 M lvl | D81: CUM | E81: 6850
B82: ii) Above + 11.0M lvl up to + 16.5M lvl | D82: CUM | E82: 7250
A83: B-03 | B83: For addition of approved quality plasticiser as directed and specified by the engineer incharge (BASF or SIKA make only)
B84: a) For early de shuttering (basic rate:90 Rs/Ltr.) | D84: LTRS | E84: 175 | F84: =E84*C84 -> 0
A85: B-04 | B85: Providing, fabricating, laying and fixing in position reinforcement for all type of RCC works at all levels, including cost of straightening, cutting, bending to required shape, binding with 16 gauge MS annealed binding wire, spacer blocks of cement mortar 1:2 with embedded binding wire of appropriate length, etc. complete as per drawings and specifications [Chairs, pins will not be measured and paid extra. Only authorized laps shall be measured and paid for] Note:- HYSD reinforcements (Fe500) of make "HY-TUF" , "Electro therm" or "ISPAT"
B86: a) High yield strength deformed bars | C86: 153 | D86: MT | E86: 69500 | F86: =E86*C86 -> 10633500
A87: B-05 | B87: Providing and fixing form work including necessary centering for footings, columns, pedestals, rafts, blocks, walls, beams, slabs, copings, pipe supports, equipment foundations, floors, roads, water retaining structures / any type of structural members etc. of any shapes including strutting, bracing, shoring, propping, staging, etc. keeping the same in position during concreting and removal of the same after a specified period, including smooth rendering of concrete surface if required, complete as per drawings and specifications (Rate to include coating formwork with approved quality of non-staining mineral oil).
B88: 1. In foundations and up to plinths (FFL) at all depths: | C88: 387 | D88: SQM | E88: 550 | F88: =E88*C88 -> 212850
B89: i) From FFL up to + 5.5 M lvl. | D89: SQM | E89: 625 | F89: =E89*C89 -> 0
A90: B-06 | B90: Providing and fixing plywood form work including necessary centering for alignment and levels for columns, blocks, pedestals, lintels, beams (regular and inverted), slabs, chajjas, copings, gutters, pardi, facias, fins, bands, walls, staircases, slopping RCC elements, rain water chutes, etc. of rectangular, square shapes, curve, including strutting, shoring, bracing, propping, staging, water retaining structure / any type of structure member, etc. keeping the same in position during the concreting and removal of the same after a specified period, etc. complete as per drawings and specifications. The framework shall ensure smooth finish surface without any additional rendering. Rate to include coating formwork with approved quality of non-staining mineral oil.
B91: 1. In foundations and up to plinths (FFL) at all depths: | D91: SQM | E91: 575 | F91: =E91*C91 -> 0
B92: i) From FFL up to + 5.0 M lvl. | C92: 926 | D92: SQM | E92: 650 | F92: =E92*C92 -> 601900
B93: ii) Above + 5.0M lvl up to + 11.0 M lvl | C93: 898 | D93: SQM | E93: 725 | F93: =E93*C93 -> 651050
B94: iii) Above + 11.0 M lvl up to + 16.5 M lvl | C94: 883 | D94: SQM | E94: 850 | F94: =E94*C94 -> 750550
B95: iv) Above + 11.0 M lvl up to + 16.5 M lvl | C95: 1396 | D95: SQM | E95: 950 | F95: =E95*C95 -> 1326200
A96: B-08 | B96: Providing free flow grouting under base plates and in pockets for holding down in pockets with GP2 of approved make including formwork, finishing, curing, etc. complete as directed by the Engineer. | D96: CUM | E96: 52500
A97: B-09 | B97: Providing and doing welding continuous or intermittent using 4.2mm welding rod in line & removing slag etc. complete.(only welding length shall be considered for mesurment.) | D97: RMT | E97: 550
A98: B-11 | B98: Providing and fixing in position in PCC/RCC work at all levels, shuttering for pockets of varying sizes as per details with necessary form work including type of form work where required and carefully removing the same for anchor and holding down bolts for columns, pedestals, pipe rack, equipment foundations, etc. all as per detailed drawing / as directed by the Engineer.
B99: a) For pocket area up to 0.01 Sq.m. and depth up to 0.30M | D99: Nos. | E99: 800 | F99: =E99*C99 -> 0
B100: b) For pocket area above 0.01 Sq.m. up to 0.03 Sq.m. and depth up to 0.30M | D100: Nos. | E100: 1050 | F100: =E100*C100 -> 0
B101: c) For pocket area above 0.03 Sq.m. up to 0.05 Sq.m. and depth up to 0.60M | D101: Nos. | E101: 1250 | F101: =E101*C101 -> 0
...

Sheet BOQ ELE. LAB 
B1: ESTIMATED BOQ FOR PROPOSED ELECTRICAL LAB CIVIL & STRUCTURAL WORKS For SUYOG ELECTRICAL LTD. NO 245/33/B,245/55/B/2,MOJE BODIDARA, TA.VADODARA, GUJARAT, INDIA.
A2: Followings are the scope of work: - Shed building Civil and Structural works (Excluding PEB shed) - Approximately 425sqm area - Machine Foundation - R.C.C. Road - Approximately 3050 sqm - Storm Water drain
A4: BOQ
A5: Sr. No. | B5: Description | C5: QTY. | D5: UNIT | E5: RATE | F5: AMOUNT
B6: SECTION- A EARTH WORK AND SOLING
A7: A-01 | B7: Cleaning the area by grass cutting, removing vegetations,roots of trees if any, scraping the existing surfaces up to 150mm, removal of all loose materials and other matters, etc. and disposing off the debris beyond the plant boundary as directed by the Engineer. | C7: 501 | D7: SQ.M. | E7: 35 | F7: =E7*C7 -> 17535
A8: A-01A | B8: Clearing the area by jungle cutting, removing trees / bushes if any from roots, scraping the existing surfaces up to 150mm, removal of all loose materials and other matters, etc. and disposing off the debris beyond the plant boundary as directed by EIC. | D8: SQ.M. | E8: 25 | F8: =E8*C8 -> 0
A9: A-02 | B9: Earth work excavation for all type of work in all soils like black cotton soil, clay, sand, soft and hard murrum, etc. but other than soft and hard rock including shoring, strutting and dewatering due to any sub soil water, rain water or any reason if required and refilling in foundations with selected excavated earth in 350mm layers, watering and consolidating to 250mm thickness, disposing off surplus excavated materials within the plant boundary at selected places, spreading evenly, leveling, etc. complete as per specifications and as directed. (Payment shall be made for 300mm from R.C.C. face for foundations and 200mm from R.C.C. face for GB)
B10: a) From average ground level up to 1.50M depth. | C10: 136 | D10: CUM | E10: 250 | F10: =E10*C10 -> 34000
B11: b) Below 1.5M up to 3M depth | D11: CUM | E11: 285 | F11: =E11*C11 -> 0
B12: c) Below 3.0M up to 4.5M depth | D12: CUM | E12: 350
B13: d) Below 4.5M up to 6.0M depth | D13: CUM | E13: 450
B14: e) Below 6.0M up to 7.5M depth | D14: CUM | E14: 575
A15: A-03 | B15: Filling in plinth & foundation pits with approved materials including spreading in 150mm layers, watering, ramming, compacting with 10MT vibro/static roller or portable compactor wherever applicable as decided by the Engineer, leveling, etc. complete. (Measurements for compacted volume is considered)
B16: a) With selected earth brought from outside | C16: 95 | D16: CUM | E16: 490 | F16: =E16*C16 -> 46550
B17: b) With approved filling sand brought from Outside. | C17: 90 | D17: CUM | E17: 1025 | F17: =E17*C17 -> 92250
B18: c) Approved quarry dust filling | D18: CUM | E18: 1150
A19: A-04 | B19: Disposing off surplus excavated materials by carting away, outside of company premises at location decided by contractor and shall be responsibility of contractor | D19: CUM | E19: 150 | F19: =E19*C19 -> 0
A20: A-04A | B20: Disposing off dumped Earth / Debris by carting away, outside of company premises at location decided by contractor and shall be responsibility of contractor
B21: a) Measurement of available material by volume | C21: 91 | D21: CUM | E21: 100 | F21: =E21*C21 -> 9100
B22: b) Measurement of available material by Dumper | D22: Nos. | E22: 3500
A23: A-05 | B23: Providing and laying black trap rubble soling at required level and grade in foundations, in plinth, ramps, etc. including hand packing, filling interstices with quarry / sand, watering and compacting with suitable vibro roller/ Static roller or earth compactor wherever applicable as decided by the Engineer to the consolidated thickness as stated below:
B24: i) 230mm thick Soling | D24: SQ.M | E24: 517
B25: ii) 150mm thick compacted layer metal packing using 63-90 mm size hand broken stone etc. as directed Engineer in charge/consultant. | C25: 447 | D25: SQ.M | E25: 310 | F25: =E25*C25 -> 138570
B26: iii) 75mm thick compacted layer metal packing using 40-63 mm size hand broken stone etc. as directed Engineer in charge/consultant. | C26: 447 | D26: SQ.M | E26: 150 | F26: =E26*C26 -> 67050
A27: A-06 | B27: Auguring(Upto 8m depth) of under ream pile foundation work in all sorts of soil viz. sand, clay, soft & hard murrum for execution of the above work. Contractor has to brought all necessary tools, tackles, equipments, manpower & supervision. Items also include carting of debris/soil, unloading, stacking, use of bentonite, spreading, levelling, compacting, consolidating surplus marterial within company premises, dewatering & one bulb as per design etc. complete as directed
B28: (a) For 250mm dia. Pile | D28: RM | E28: 300
B29: (b) For 300mm dia. Pile | D29: RM | E29: 350 | F29: =E29*C29 -> 0
B30: (c) For 350mm dia. Pile | C30: 375 | D30: RM | E30: 425 | F30: =E30*C30 -> 159375
B31: (d) For 400mm dia. Pile | D31: RM | E31: 495 | F31: =E31*C31 -> 0
A32: A-07 | B32: -do- as per item no. A-06 but for construction of extra bulb in the pile at any level. The size of the bulb will be as per design.
B33: (a) For 250mm dia. Pile | D33: NO | E33: 300
B34: (b) For 300mm dia. Pile | D34: NO | E34: 400
B35: (c) For 350mm dia. Pile | D35: NO | E35: 450
B36: (d) For 400mm dia. Pile | D36: NO | E36: 500
B37: TOTAL OF SECTION `A` | F37: =SUM(F7:F36) -> 564430
B38: SECTION - B CONCRETE
A39: B-01 | B39: Providing and laying Plain cement concrete below all R.C.C. member, floors, ramps, chembers etc. with 20mm nominal size graded stone aggregates of approved quality (black trap only) including leveling, compacting, curing and form work if any, etc. complete.
B40: a) Mix 1: 4: 8 | C40: 43 | D40: CUM | E40: 4100 | F40: =E40*C40 -> 176300
B41: b) Mix 1: 3: 6 | D41: CUM | E41: 4175 | F41: =E41*C41 -> 0
A42: B-02 | B42: Providing and laying reinforced cement concrete with 20mm and down size graded stone aggregates in all types of concrete works such as footings, columns, pedestals, rafts, beams, lofts, slabs, walls, lintels, chajjas, canopies, facias, fins, bands, shelves, staircases, all other any type of structural members, pits, chambers, rain water chutes, gutters, pardi, curbs, pipe racks, & equipment foundations, etc. of square, rectangular, hexagonal, octagonal and circular shapes including leaving pockets, vatas, openings in slabs, including vibrating, tamping, finishing, curing and rendering if required, etc. complete as per drawings and specifications but excluding the cost of formwork and reinforcement. (No false staging shall be given.) Cement Make: Ultratech / JK Lakshmi / Ambuja - OPC 53 grade (Applicable to all items)
B43: a) M : 20 Grade (Min. Cement - 300 KG/M3)
B44: 1. In foundations and up to plinths (FFL) at all depths: | D44: CUM | E44: 5450
B45: i) From FFL up to + 5.5 M lvl. | D45: CUM | E45: 5950
B46: b) M: 25 Grade (Min. Cement - 340 KG/M3)
B47: 1. In foundations and up to plinths (FFL) at all depths: | C47: 55 | D47: CUM | E47: 5850 | F47: =E47*C47 -> 321750
B48: i) From FFL up to + 5.0 M lvl. | C48: 12 | D48: CUM | E48: 6175 | F48: =E48*C48 -> 74100
B49: ii) Above + 5.0M lvl up to + 11.0 M lvl | D49: CUM | E49: 6350
B50: c) Extra for M30 Concrete in place of M25 (Min. Cement- 370 KG/M3) | D50: CUM | E50: 950
A51: B-02A | B51: Ready Mix Concreate (Prior Permission shall be taken before using Ready Mix Concrete from engineer Incharge)
B52: Providing and laying ready mix concrete with 20mm and down size graded stone aggregates Without flyash in all types of concrete works such as footings, columns, pedestals, rafts, beams, lofts, slabs, walls, lintels, chajjas, canopies, facias, fins, bands, shelves, staircases, pits, chambers, rain water chutes, gutt­ers, pardi, curbs, pipe racks, & equipment foundations, etc. of square, rectangular, hexagonal, octagonal and circular shapes including leaving pockets, openings in slabs, vibrating, tamping, finishing, curing and rendering if required, etc. complete as per drawings and specifications but excluding the cost of formwork and reinforcement. Cement: OPC53 grade Ultra tech, Ambuja Supply of cement will be in contractor's scope. Mix Design has to be approved from Consultant.
A53: B-02 A1 | B53: In foundations and up to plinths (FFL) at all depths:
B54: a) M: 20 Grade (min . Cement : 300 kg/m3) | D54: Cu.m | E54: 5450
B55: b) M: 25 Grade (min . Cement : 340 kg/m3) | D55: Cu.m | E55: 5850 | F55: =E55*C55 -> 0
B56: c) Extra for M30 Concrete in place of M25 (Min. Cement- 370 KG/M3) | D56: Cu.m | E56: 950
A57: B-02 A2 | B57: In superstructure above finished floor level at all heights.
B58: a) M : 20 Grade
B59: i) From FFL up to + 5.5M lvl. | D59: Cu.m | E59: 5700 | F59: =E59*C59 -> 0
B60: ii) Above + 5.5M lvl. | D60: Cu.m
B61: b) M : 25 Grade
B62: i) From FFL up to + 5.5M lvl. | D62: Cu.m | E62: 5900 | F62: =E62*C62 -> 0
B63: ii) Above + 5.5M lvl up to + 11.0M lvl | D63: Cu.m | E63: 6650
B64: c) Extra for M30 Concrete in place of M25 (Min. Cement- 370 KG/M3) | D64: Cu.m | E64: 950
A65: B-02B | B65: Providing and laying reinforced cement concrete with 20mm and down size graded stone aggregates in PILE. of circular shapes including tamping, curing and development of pile- including use of trimi, breaking (Upto 0.60m length), cleanning etc. complete as per drawings and specifications but excluding the cost of formwork and reinforcement. (USE GRADE OF CONC. M25)
B66: (a) For 250mm dia. Pile | D66: CUM | E66: 5600
B67: (b) For 300mm dia. Pile | D67: CUM | E67: 5369 | F67: =E67*C67 -> 0
B68: (b) For 350mm dia. Pile | C68: 41 | D68: CUM | E68: 5650 | F68: =E68*C68 -> 231650
B69: (c) For 400mm dia. Pile | D69: CUM | E69: 5650 | F69: =E69*C69 -> 0
A70: B-02C | B70: Providing and laying reinforced cement concrete with 20mm and down size graded stone aggregates in PRECAST concrete works for storm water trench, Chamber Cover etc. of square, rectangular, hexagonal, octagonal and circular shapes including leaving pockets, openings in covers, vibrating, tamping, finishing, curing and rendering if required, etc. complete as per drawings and specifications. The rate includes the cost of formwork and installing the elements in line and level. (Reinforcement steel is paid seperately in item no. B-05 )
B71: (a) M25 grade | D71: CUM | E71: 9500
B72: (b) M30 grade | D72: CUM | E72: 9500
A73: B-02D | B73: Providing and laying M25 Grade Reinforced cement concrete for water retaining structures/Cable Trech / basement structures/over head tanks, ETP, scale pit, basins sumps / sump pits, manholes, inspection chambers of sewage / drainage lines etc at any level and location. Including addition of water proofing compound WAREP 1000L Manufactured by Thermax Ltd. , FOSROC-CONPLAST '-X4211C- or equivalent approved make in concrete as per approved manufacturer's specification, including pressure cement grouting of mix 1:1 with water proofing additives MAXGROUT 100 MANUFACTURED by THERMAX LTD.or equivalent at construction joints, weak spot / honey combs and testing the same for water tightness as per requirements of IS 3370 and making good defects / leakages as instructed by Engineers / Owners. Rate also to include cost of water proofing compound, testing and rectification of leakage etc
B74: a) M: 25 Grade (Minimum Cement : 340 kg/M3)
B75: 1. In foundations and up to plinths (FFL) at all depths: | D75: CUM | E75: 5750 | F75: =E75*C75 -> 0
B76: i) From FFL up to + 5.5 M lvl. | D76: CUM | E76: 6650
B77: ii) Above + 5.5M lvl up to + 11.0 M lvl | D77: CUM | E77: 6850
B78: ii) Above + 11.0M lvl up to + 16.5M lvl | D78: CUM | E78: 7250
A79: B-03 | B79: For addition of approved quality plasticiser as directed and specified by the engineer incharge (BASF or SIKA make only)
B80: a) For early de shuttering (basic rate:90 Rs/Ltr.) | D80: LTRS | E80: 175 | F80: =E80*C80 -> 0
A81: B-04 | B81: Providing, fabricating, laying and fixing in position reinforcement for all type of RCC works at all levels, including cost of straightening, cutting, bending to required shape, binding with 16 gauge MS annealed binding wire, spacer blocks of cement mortar 1:2 with embedded binding wire of appropriate length, etc. complete as per drawings and specifications [Chairs, pins will not be measured and paid extra. Only authorized laps shall be measured and paid for] Note:- HYSD reinforcements (Fe500) of make "HY-TUF" , "Electro therm" or "ISPAT"
B82: a) High yield strength deformed bars | C82: 17 | D82: MT | E82: 69500 | F82: =E82*C82 -> 1181500
A83: B-05 | B83: Providing and fixing form work including necessary centering for footings, columns, pedestals, rafts, blocks, walls, beams, slabs, copings, pipe supports, equipment foundations, floors, roads, water retaining structures / any type of structural members etc. of any shapes including strutting, bracing, shoring, propping, staging, etc. keeping the same in position during concreting and removal of the same after a specified period, including smooth rendering of concrete surface if required, complete as per drawings and specifications (Rate to include coating formwork with approved quality of non-staining mineral oil).
B84: 1. In foundations and up to plinths (FFL) at all depths: | C84: 219 | D84: SQM | E84: 550 | F84: =C84*E84 -> 120450
B85: i) From FFL up to + 5.5 M lvl. | D85: SQM | E85: 625
A86: B-06 | B86: Providing and fixing plywood form work including necessary centering for alignment and levels for columns, blocks, pedestals, lintels, beams (regular and inverted), slabs, chajjas, copings, gutters, pardi, facias, fins, bands, walls, staircases, slopping RCC elements, rain water chutes, etc. of rectangular, square shapes, curve, including strutting, shoring, bracing, propping, staging, water retaining structure / any type of structure member, etc. keeping the same in position during the concreting and removal of the same after a specified period, etc. complete as per drawings and specifications. The framework shall ensure smooth finish surface without any additional rendering. Rate to include coating formwork with approved quality of non-staining mineral oil.
B87: 1. In foundations and up to plinths (FFL) at all depths: | D87: SQM | E87: 575
B88: i) From FFL up to + 5.5 M lvl. | C88: 119 | D88: SQM | E88: 650 | F88: =E88*C88 -> 77350
B89: ii) Above + 5.5M lvl up to + 11.0 M lvl | D89: SQM | E89: 725
B90: ii) Above + 11.0 M lvl up to + 16.5 M lvl | D90: SQM | E90: 850
A91: B-08 | B91: Providing free flow grouting under base plates and in pockets for holding down in pockets with GP2 of approved make including formwork, finishing, curing, etc. complete as directed by the Engineer. | C91: 0.5 | D91: CUM | E91: 52500 | F91: =E91*C91 -> 26250
A92: B-09 | B92: Providing and doing welding continuous or intermittent using 4.2mm welding rod in line & removing slag etc. complete.(only welding length shall be considered for mesurment.) | D92: RMT | E92: 550
A93: B-11 | B93: Providing and fixing in position in PCC/RCC work at all levels, shuttering for pockets of varying sizes as per details with necessary form work including type of form work where required and carefully removing the same for anchor and holding down bolts for columns, pedestals, pipe rack, equipment foundations, etc. all as per detailed drawing / as directed by the Engineer.
B94: a) For pocket area up to 0.01 Sq.m. and depth up to 0.30M | D94: Nos. | E94: 800 | F94: =E94*C94 -> 0
B95: b) For pocket area above 0.01 Sq.m. up to 0.03 Sq.m. and depth up to 0.30M | D95: Nos. | E95: 1050 | F95: =E95*C95 -> 0
B96: c) For pocket area above 0.03 Sq.m. up to 0.05 Sq.m. and depth up to 0.60M | D96: Nos. | E96: 1250 | F96: =E96*C96 -> 0
B97: d) For pocket area up to 0.01 Sq.m. and depth up to 0.75M | D97: Nos. | E97: 1250 | F97: =E97*C97 -> 0
B98: e) For pocket area above 0.01 Sq.m. up to 0.03 Sq.m. and depth up to 0.75M | D98: Nos. | E98: 1350 | F98: =E98*C98 -> 0
B99: f) For pocket area above 0.03 Sq.m. up to 0.05 Sq.m. and depth up to 1.0M | D99: Nos. | E99: 2000 | F99: =E99*C99 -> 0
B100: g) For pocket area up to 0.01 Sq.m. and depth up to 1.25M | D100: Nos. | E100: 1950 | F100: =E100*C100 -> 0
B101: h) For pocket area above 0.01 Sq.m. up to 0.03 Sq.m. and depth up to 1.25M | D101: Nos. | E101: 2250 | F101: =E101*C101 -> 0
...

Sheet BOQ-ADMIN
B1: ESTIMATED BOQ FOR PROPOSED ADMIN CIVIL & STRUCTURAL WORKS For SUYOG ELECTRICAL LTD. NO 245/33/B,245/55/B/2,MOJE BODIDARA, TA.VADODARA, GUJARAT, INDIA.
A2: Followings are the scope of work: - ADMIN building Civil and Structural works (Excluding PEB shed) - Approximately 315 sqm area - Machine Foundation - R.C.C. Road - Approximately 3050 sqm - Storm Water drain
A4: BOQ
A5: Sr. No. | B5: Description | C5: QTY. | D5: UNIT | E5: RATE | F5: AMOUNT
B6: SECTION- A EARTH WORK AND SOLING
A7: A-01 | B7: Cleaning the area by grass cutting, removing vegetations,roots of trees if any, scraping the existing surfaces up to 150mm, removal of all loose materials and other matters, etc. and disposing off the debris beyond the plant boundary as directed by the Engineer. | C7: 378 | D7: SQ.M. | E7: 35 | F7: =E7*C7 -> 13230
A8: A-01A | B8: Clearing the area by jungle cutting, removing trees / bushes if any from roots, scraping the existing surfaces up to 150mm, removal of all loose materials and other matters, etc. and disposing off the debris beyond the plant boundary as directed by EIC. | D8: SQ.M. | E8: 25 | F8: =E8*C8 -> 0
A9: A-02 | B9: Earth work excavation for all type of work in all soils like black cotton soil, clay, sand, soft and hard murrum, etc. but other than soft and hard rock including shoring, strutting and dewatering due to any sub soil water, rain water or any reason if required and refilling in foundations with selected excavated earth in 350mm layers, watering and consolidating to 250mm thickness, disposing off surplus excavated materials within the plant boundary at selected places, spreading evenly, leveling, etc. complete as per specifications and as directed. (Payment shall be made for 300mm from R.C.C. face for foundations and 200mm from R.C.C. face for GB)
B10: a) From average ground level up to 1.50M depth. | C10: 322 | D10: CUM | E10: 250 | F10: =E10*C10 -> 80500
B11: b) Below 1.5M up to 3M depth | D11: CUM | E11: 285 | F11: =E11*C11 -> 0
B12: c) Below 3.0M up to 4.5M depth | D12: CUM | E12: 350
B13: d) Below 4.5M up to 6.0M depth | D13: CUM | E13: 450
B14: e) Below 6.0M up to 7.5M depth | D14: CUM | E14: 575
A15: A-03 | B15: Filling in plinth & foundation pits with approved materials including spreading in 150mm layers, watering, ramming, compacting with 10MT vibro/static roller or portable compactor wherever applicable as decided by the Engineer, leveling, etc. complete. (Measurements for compacted volume is considered)
B16: a) With selected earth brought from outside | C16: 72 | D16: CUM | E16: 490 | F16: =E16*C16 -> 35280
B17: b) With approved filling sand brought from Outside. | C17: 67 | D17: CUM | E17: 1025 | F17: =E17*C17 -> 68675
B18: c) Approved quarry dust filling | D18: CUM | E18: 1150
A19: A-04 | B19: Disposing off surplus excavated materials by carting away, outside of company premises at location decided by contractor and shall be responsibility of contractor | C19: 192 | D19: CUM | E19: 150 | F19: =E19*C19 -> 28800
A20: A-04A | B20: Disposing off dumped Earth / Debris by carting away, outside of company premises at location decided by contractor and shall be responsibility of contractor
B21: a) Measurement of available material by volume | D21: CUM | E21: 100 | F21: =E21*C21 -> 0
B22: b) Measurement of available material by Dumper | D22: Nos. | E22: 3500
A23: A-05 | B23: Providing and laying black trap rubble soling at required level and grade in foundations, in plinth, ramps, etc. including hand packing, filling interstices with quarry / sand, watering and compacting with suitable vibro roller/ Static roller or earth compactor wherever applicable as decided by the Engineer to the consolidated thickness as stated below:
B24: i) 230mm thick Soling | D24: SQ.M | E24: 517
B25: ii) 150mm thick compacted layer metal packing using 63-90 mm size hand broken stone etc. as directed Engineer in charge/consultant. | C25: 378 | D25: SQ.M | E25: 310 | F25: =E25*C25 -> 117180
B26: iii) 75mm thick compacted layer metal packing using 40-63 mm size hand broken stone etc. as directed Engineer in charge/consultant. | C26: 340 | D26: SQ.M | E26: 150 | F26: =E26*C26 -> 51000
A27: A-06 | B27: Auguring(Upto 8m depth) of under ream pile foundation work in all sorts of soil viz. sand, clay, soft & hard murrum for execution of the above work. Contractor has to brought all necessary tools, tackles, equipments, manpower & supervision. Items also include carting of debris/soil, unloading, stacking, use of bentonite, spreading, levelling, compacting, consolidating surplus marterial within company premises, dewatering & one bulb as per design etc. complete as directed
B28: (a) For 250mm dia. Pile | D28: RM | E28: 300
B29: (b) For 300mm dia. Pile | D29: RM | E29: 350 | F29: =E29*C29 -> 0
B30: (c) For 350mm dia. Pile | D30: RM | E30: 425 | F30: =E30*C30 -> 0
B31: (d) For 450 mm dia. Pile | C31: 698 | D31: RM | E31: 495 | F31: =E31*C31 -> 345510
A32: A-07 | B32: -do- as per item no. A-06 but for construction of extra bulb in the pile at any level. The size of the bulb will be as per design.
B33: (a) For 250mm dia. Pile | D33: NO | E33: 300
B34: (b) For 300mm dia. Pile | D34: NO | E34: 400
B35: (c) For 350mm dia. Pile | D35: NO | E35: 450
B36: (d) For 400mm dia. Pile | D36: NO | E36: 500
B37: TOTAL OF SECTION `A` | F37: =SUM(F7:F36) -> 740175
B38: SECTION - B CONCRETE
A39: B-01 | B39: Providing and laying Plain cement concrete below all R.C.C. member, floors, ramps, chembers etc. with 20mm nominal size graded stone aggregates of approved quality (black trap only) including leveling, compacting, curing and form work if any, etc. complete.
B40: a) Mix 1: 4: 8 | C40: 43 | D40: CUM | E40: 4100 | F40: =E40*C40 -> 176300
B41: b) Mix 1: 3: 6 | D41: CUM | E41: 4175 | F41: =E41*C41 -> 0
A42: B-02 | B42: Providing and laying reinforced cement concrete with 20mm and down size graded stone aggregates in all types of concrete works such as footings, columns, pedestals, rafts, beams, lofts, slabs, walls, lintels, chajjas, canopies, facias, fins, bands, shelves, staircases, all other any type of structural members, pits, chambers, rain water chutes, gutters, pardi, curbs, pipe racks, & equipment foundations, etc. of square, rectangular, hexagonal, octagonal and circular shapes including leaving pockets, vatas, openings in slabs, including vibrating, tamping, finishing, curing and rendering if required, etc. complete as per drawings and specifications but excluding the cost of formwork and reinforcement. (No false staging shall be given.) Cement Make: Ultratech / JK Lakshmi / Ambuja - OPC 53 grade (Applicable to all items)
B43: a) M : 20 Grade (Min. Cement - 300 KG/M3)
B44: 1. In foundations and up to plinths (FFL) at all depths: | D44: CUM | E44: 5450
B45: i) From FFL up to + 5.5 M lvl. | D45: CUM | E45: 5950
B46: b) M: 25 Grade (Min. Cement - 340 KG/M3)
B47: 1. In foundations and up to plinths (FFL) at all depths: | C47: 129 | D47: CUM | E47: 5850 | F47: =E47*C47 -> 754650
B48: i) From FFL up to + 5.0 M lvl. | C48: 82 | D48: CUM | E48: 6175 | F48: =E48*C48 -> 506350
B49: ii) Above + 5.0M lvl up to + 11.0 M lvl | D49: CUM | E49: 6350
B50: c) Extra for M30 Concrete in place of M25 (Min. Cement- 370 KG/M3) | D50: CUM | E50: 950
A51: B-02A | B51: Ready Mix Concreate (Prior Permission shall be taken before using Ready Mix Concrete from engineer Incharge)
B52: Providing and laying ready mix concrete with 20mm and down size graded stone aggregates Without flyash in all types of concrete works such as footings, columns, pedestals, rafts, beams, lofts, slabs, walls, lintels, chajjas, canopies, facias, fins, bands, shelves, staircases, pits, chambers, rain water chutes, gutt­ers, pardi, curbs, pipe racks, & equipment foundations, etc. of square, rectangular, hexagonal, octagonal and circular shapes including leaving pockets, openings in slabs, vibrating, tamping, finishing, curing and rendering if required, etc. complete as per drawings and specifications but excluding the cost of formwork and reinforcement. Cement: OPC53 grade Ultra tech, Ambuja Supply of cement will be in contractor's scope. Mix Design has to be approved from Consultant.
A53: B-02 A1 | B53: In foundations and up to plinths (FFL) at all depths:
B54: a) M: 20 Grade (min . Cement : 300 kg/m3) | D54: Cu.m | E54: 5450
B55: b) M: 25 Grade (min . Cement : 340 kg/m3) | D55: Cu.m | E55: 5850 | F55: =E55*C55 -> 0
B56: c) Extra for M30 Concrete in place of M25 (Min. Cement- 370 KG/M3) | D56: Cu.m | E56: 950
A57: B-02 A2 | B57: In superstructure above finished floor level at all heights.
B58: a) M : 20 Grade
B59: i) From FFL up to + 5.5M lvl. | D59: Cu.m | E59: 5700 | F59: =E59*C59 -> 0
B60: ii) Above + 5.5M lvl. | D60: Cu.m
B61: b) M : 25 Grade
B62: i) From FFL up to + 5.5M lvl. | D62: Cu.m | E62: 5900 | F62: =E62*C62 -> 0
B63: ii) Above + 5.5M lvl up to + 11.0M lvl | D63: Cu.m | E63: 6650
B64: c) Extra for M30 Concrete in place of M25 (Min. Cement- 370 KG/M3) | D64: Cu.m | E64: 950
A65: B-02B | B65: Providing and laying reinforced cement concrete with 20mm and down size graded stone aggregates in PILE. of circular shapes including tamping, curing and development of pile- including use of trimi, breaking (Upto 0.60m length), cleanning etc. complete as per drawings and specifications but excluding the cost of formwork and reinforcement. (USE GRADE OF CONC. M25)
B66: (a) For 250mm dia. Pile | D66: CUM | E66: 5600
B67: (b) For 300mm dia. Pile | D67: CUM | E67: 5369 | F67: =E67*C67 -> 0
B68: (b) For 350mm dia. Pile | D68: CUM | E68: 5650 | F68: =E68*C68 -> 0
B69: (c) For 450mm dia. Pile | C69: 97 | D69: CUM | E69: 5650 | F69: =E69*C69 -> 548050
A70: B-02C | B70: Providing and laying reinforced cement concrete with 20mm and down size graded stone aggregates in PRECAST concrete works for storm water trench, Chamber Cover etc. of square, rectangular, hexagonal, octagonal and circular shapes including leaving pockets, openings in covers, vibrating, tamping, finishing, curing and rendering if required, etc. complete as per drawings and specifications. The rate includes the cost of formwork and installing the elements in line and level. (Reinforcement steel is paid seperately in item no. B-05 )
B71: (a) M25 grade | D71: CUM | E71: 9500
B72: (b) M30 grade | D72: CUM | E72: 9500
A73: B-02D | B73: Providing and laying M25 Grade Reinforced cement concrete for water retaining structures/Cable Trech / basement structures/over head tanks, ETP, scale pit, basins sumps / sump pits, manholes, inspection chambers of sewage / drainage lines etc at any level and location. Including addition of water proofing compound WAREP 1000L Manufactured by Thermax Ltd. , FOSROC-CONPLAST '-X4211C- or equivalent approved make in concrete as per approved manufacturer's specification, including pressure cement grouting of mix 1:1 with water proofing additives MAXGROUT 100 MANUFACTURED by THERMAX LTD.or equivalent at construction joints, weak spot / honey combs and testing the same for water tightness as per requirements of IS 3370 and making good defects / leakages as instructed by Engineers / Owners. Rate also to include cost of water proofing compound, testing and rectification of leakage etc
B74: a) M: 25 Grade (Minimum Cement : 340 kg/M3)
B75: 1. In foundations and up to plinths (FFL) at all depths: | D75: CUM | E75: 5750 | F75: =E75*C75 -> 0
B76: i) From FFL up to + 5.5 M lvl. | D76: CUM | E76: 6650
B77: ii) Above + 5.5M lvl up to + 11.0 M lvl | D77: CUM | E77: 6850
B78: ii) Above + 11.0M lvl up to + 16.5M lvl | D78: CUM | E78: 7250
A79: B-03 | B79: For addition of approved quality plasticiser as directed and specified by the engineer incharge (BASF or SIKA make only)
B80: a) For early de shuttering (basic rate:90 Rs/Ltr.) | D80: LTRS | E80: 175 | F80: =E80*C80 -> 0
A81: B-04 | B81: Providing, fabricating, laying and fixing in position reinforcement for all type of RCC works at all levels, including cost of straightening, cutting, bending to required shape, binding with 16 gauge MS annealed binding wire, spacer blocks of cement mortar 1:2 with embedded binding wire of appropriate length, etc. complete as per drawings and specifications [Chairs, pins will not be measured and paid extra. Only authorized laps shall be measured and paid for] Note:- HYSD reinforcements (Fe500) of make "HY-TUF" , "Electro therm" or "ISPAT"
B82: a) High yield strength deformed bars | C82: 24 | D82: MT | E82: 69500 | F82: =E82*C82 -> 1668000
A83: B-05 | B83: Providing and fixing form work including necessary centering for footings, columns, pedestals, rafts, blocks, walls, beams, slabs, copings, pipe supports, equipment foundations, floors, roads, water retaining structures / any type of structural members etc. of any shapes including strutting, bracing, shoring, propping, staging, etc. keeping the same in position during concreting and removal of the same after a specified period, including smooth rendering of concrete surface if required, complete as per drawings and specifications (Rate to include coating formwork with approved quality of non-staining mineral oil).
B84: 1. In foundations and up to plinths (FFL) at all depths: | C84: 252 | D84: SQM | E84: 550 | F84: =C84*E84 -> 138600
B85: i) From FFL up to + 5.5 M lvl. | D85: SQM | E85: 625
A86: B-06 | B86: Providing and fixing plywood form work including necessary centering for alignment and levels for columns, blocks, pedestals, lintels, beams (regular and inverted), slabs, chajjas, copings, gutters, pardi, facias, fins, bands, walls, staircases, slopping RCC elements, rain water chutes, etc. of rectangular, square shapes, curve, including strutting, shoring, bracing, propping, staging, water retaining structure / any type of structure member, etc. keeping the same in position during the concreting and removal of the same after a specified period, etc. complete as per drawings and specifications. The framework shall ensure smooth finish surface without any additional rendering. Rate to include coating formwork with approved quality of non-staining mineral oil.
B87: 1. In foundations and up to plinths (FFL) at all depths: | D87: SQM | E87: 575
B88: i) From FFL up to + 5.5 M lvl. | C88: 756 | D88: SQM | E88: 650 | F88: =E88*C88 -> 491400
B89: ii) Above + 5.5M lvl up to + 11.0 M lvl | D89: SQM | E89: 725
B90: ii) Above + 11.0 M lvl up to + 16.5 M lvl | D90: SQM | E90: 850
A91: B-08 | B91: Providing free flow grouting under base plates and in pockets for holding down in pockets with GP2 of approved make including formwork, finishing, curing, etc. complete as directed by the Engineer. | D91: CUM | E91: 52500 | F91: =E91*C91 -> 0
A92: B-09 | B92: Providing and doing welding continuous or intermittent using 4.2mm welding rod in line & removing slag etc. complete.(only welding length shall be considered for mesurment.) | D92: RMT | E92: 550
A93: B-11 | B93: Providing and fixing in position in PCC/RCC work at all levels, shuttering for pockets of varying sizes as per details with necessary form work including type of form work where required and carefully removing the same for anchor and holding down bolts for columns, pedestals, pipe rack, equipment foundations, etc. all as per detailed drawing / as directed by the Engineer.
B94: a) For pocket area up to 0.01 Sq.m. and depth up to 0.30M | D94: Nos. | E94: 800 | F94: =E94*C94 -> 0
B95: b) For pocket area above 0.01 Sq.m. up to 0.03 Sq.m. and depth up to 0.30M | D95: Nos. | E95: 1050 | F95: =E95*C95 -> 0
B96: c) For pocket area above 0.03 Sq.m. up to 0.05 Sq.m. and depth up to 0.60M | D96: Nos. | E96: 1250 | F96: =E96*C96 -> 0
B97: d) For pocket area up to 0.01 Sq.m. and depth up to 0.75M | D97: Nos. | E97: 1250 | F97: =E97*C97 -> 0
B98: e) For pocket area above 0.01 Sq.m. up to 0.03 Sq.m. and depth up to 0.75M | D98: Nos. | E98: 1350 | F98: =E98*C98 -> 0
B99: f) For pocket area above 0.03 Sq.m. up to 0.05 Sq.m. and depth up to 1.0M | D99: Nos. | E99: 2000 | F99: =E99*C99 -> 0
B100: g) For pocket area up to 0.01 Sq.m. and depth up to 1.25M | D100: Nos. | E100: 1950 | F100: =E100*C100 -> 0
B101: h) For pocket area above 0.01 Sq.m. up to 0.03 Sq.m. and depth up to 1.25M | D101: Nos. | E101: 2250 | F101: =E101*C101 -> 0
...

Sheet BOQ -SECURITY
B1: ESTIMATED BOQ FOR PROPOSED SECURITY CIVIL & STRUCTURAL WORKS For SUYOG ELECTRICAL LTD. NO 245/33/B,245/55/B/2,MOJE BODIDARA, TA.VADODARA, GUJARAT, INDIA.
A2: Followings are the scope of work: - Shed building Civil and Structural works (Excluding PEB shed) - Approximately 16sqm area - Machine Foundation - R.C.C. Road - Approximately 3050 sqm - Storm Water drain
A3: BOQ
A4: Sr. No. | B4: Description | C4: QTY. | D4: UNIT | E4: RATE | F4: AMOUNT
B5: SECTION- A EARTH WORK AND SOLING
A6: A-01 | B6: Cleaning the area by grass cutting, removing vegetations,roots of trees if any, scraping the existing surfaces up to 150mm, removal of all loose materials and other matters, etc. and disposing off the debris beyond the plant boundary as directed by the Engineer. | C6: 31 | D6: SQ.M. | E6: 35 | F6: =E6*C6 -> 1085
A7: A-01A | B7: Clearing the area by jungle cutting, removing trees / bushes if any from roots, scraping the existing surfaces up to 150mm, removal of all loose materials and other matters, etc. and disposing off the debris beyond the plant boundary as directed by EIC. | D7: SQ.M. | E7: 25 | F7: =E7*C7 -> 0
A8: A-02 | B8: Earth work excavation for all type of work in all soils like black cotton soil, clay, sand, soft and hard murrum, etc. but other than soft and hard rock including shoring, strutting and dewatering due to any sub soil water, rain water or any reason if required and refilling in foundations with selected excavated earth in 350mm layers, watering and consolidating to 250mm thickness, disposing off surplus excavated materials within the plant boundary at selected places, spreading evenly, leveling, etc. complete as per specifications and as directed. (Payment shall be made for 300mm from R.C.C. face for foundations and 200mm from R.C.C. face for GB)
B9: a) From average ground level up to 1.50M depth. | C9: 5 | D9: CUM | E9: 250 | F9: =E9*C9 -> 1250
B10: b) Below 1.5M up to 3M depth | D10: CUM | E10: 285 | F10: =E10*C10 -> 0
B11: c) Below 3.0M up to 4.5M depth | D11: CUM | E11: 350
B12: d) Below 4.5M up to 6.0M depth | D12: CUM | E12: 450
B13: e) Below 6.0M up to 7.5M depth | D13: CUM | E13: 575
A14: A-03 | B14: Filling in plinth & foundation pits with approved materials including spreading in 150mm layers, watering, ramming, compacting with 10MT vibro/static roller or portable compactor wherever applicable as decided by the Engineer, leveling, etc. complete. (Measurements for compacted volume is considered)
B15: a) With selected earth brought from outside | C15: 5 | D15: CUM | E15: 490 | F15: =E15*C15 -> 2450
B16: b) With approved filling sand brought from Outside. | C16: 4 | D16: CUM | E16: 1025 | F16: =E16*C16 -> 4100
B17: c) Approved quarry dust filling | D17: CUM | E17: 1150
A18: A-04 | B18: Disposing off surplus excavated materials by carting away, outside of company premises at location decided by contractor and shall be responsibility of contractor | C18: 5 | D18: CUM | E18: 150 | F18: =E18*C18 -> 750
A19: A-04A | B19: Disposing off dumped Earth / Debris by carting away, outside of company premises at location decided by contractor and shall be responsibility of contractor
B20: a) Measurement of available material by volume | D20: CUM | E20: 100 | F20: =E20*C20 -> 0
B21: b) Measurement of available material by Dumper | D21: Nos. | E21: 3500
A22: A-05 | B22: Providing and laying black trap rubble soling at required level and grade in foundations, in plinth, ramps, etc. including hand packing, filling interstices with quarry / sand, watering and compacting with suitable vibro roller/ Static roller or earth compactor wherever applicable as decided by the Engineer to the consolidated thickness as stated below:
B23: i) 230mm thick Soling | D23: SQ.M | E23: 517
B24: ii) 150mm thick compacted layer metal packing using 63-90 mm size hand broken stone etc. as directed Engineer in charge/consultant. | C24: 20 | D24: SQ.M | E24: 310 | F24: =E24*C24 -> 6200
B25: iii) 75mm thick compacted layer metal packing using 40-63 mm size hand broken stone etc. as directed Engineer in charge/consultant. | C25: 19 | D25: SQ.M | E25: 150 | F25: =E25*C25 -> 2850
A26: A-06 | B26: Auguring(Upto 8m depth) of under ream pile foundation work in all sorts of soil viz. sand, clay, soft & hard murrum for execution of the above work. Contractor has to brought all necessary tools, tackles, equipments, manpower & supervision. Items also include carting of debris/soil, unloading, stacking, use of bentonite, spreading, levelling, compacting, consolidating surplus marterial within company premises, dewatering & one bulb as per design etc. complete as directed
B27: (a) For 250mm dia. Pile | D27: RM | E27: 300
B28: (b) For 300mm dia. Pile | D28: RM | E28: 350 | F28: =E28*C28 -> 0
B29: (c) For 350mm dia. Pile | C29: 35 | D29: RM | E29: 425 | F29: =E29*C29 -> 14875
B30: (d) For 400mm dia. Pile | D30: RM | E30: 495 | F30: =E30*C30 -> 0
A31: A-07 | B31: -do- as per item no. A-06 but for construction of extra bulb in the pile at any level. The size of the bulb will be as per design.
B32: (a) For 250mm dia. Pile | D32: NO | E32: 300
B33: (b) For 300mm dia. Pile | D33: NO | E33: 400
B34: (c) For 350mm dia. Pile | D34: NO | E34: 450
B35: (d) For 400mm dia. Pile | D35: NO | E35: 500
B36: TOTAL OF SECTION `A` | F36: =SUM(F6:F35) -> 33560
B37: SECTION - B CONCRETE
A38: B-01 | B38: Providing and laying Plain cement concrete below all R.C.C. member, floors, ramps, chembers etc. with 20mm nominal size graded stone aggregates of approved quality (black trap only) including leveling, compacting, curing and form work if any, etc. complete.
B39: a) Mix 1: 4: 8 | C39: 2 | D39: CUM | E39: 4100 | F39: =E39*C39 -> 8200
B40: b) Mix 1: 3: 6 | D40: CUM | E40: 4175 | F40: =E40*C40 -> 0
A41: B-02 | B41: Providing and laying reinforced cement concrete with 20mm and down size graded stone aggregates in all types of concrete works such as footings, columns, pedestals, rafts, beams, lofts, slabs, walls, lintels, chajjas, canopies, facias, fins, bands, shelves, staircases, all other any type of structural members, pits, chambers, rain water chutes, gutters, pardi, curbs, pipe racks, & equipment foundations, etc. of square, rectangular, hexagonal, octagonal and circular shapes including leaving pockets, vatas, openings in slabs, including vibrating, tamping, finishing, curing and rendering if required, etc. complete as per drawings and specifications but excluding the cost of formwork and reinforcement. (No false staging shall be given.) Cement Make: Ultratech / JK Lakshmi / Ambuja - OPC 53 grade (Applicable to all items)
B42: a) M : 20 Grade (Min. Cement - 300 KG/M3)
B43: 1. In foundations and up to plinths (FFL) at all depths: | D43: CUM | E43: 5450
B44: i) From FFL up to + 5.5 M lvl. | D44: CUM | E44: 5950
B45: b) M: 25 Grade (Min. Cement - 340 KG/M3)
B46: 1. In foundations and up to plinths (FFL) at all depths: | C46: 4 | D46: CUM | E46: 5850 | F46: =E46*C46 -> 23400
B47: i) From FFL up to + 5.0 M lvl. | C47: 6 | D47: CUM | E47: 6175 | F47: =E47*C47 -> 37050
B48: ii) Above + 5.0M lvl up to + 11.0 M lvl | D48: CUM | E48: 6350
B49: c) Extra for M30 Concrete in place of M25 (Min. Cement- 370 KG/M3) | D49: CUM | E49: 950
A50: B-02A | B50: Ready Mix Concreate (Prior Permission shall be taken before using Ready Mix Concrete from engineer Incharge)
B51: Providing and laying ready mix concrete with 20mm and down size graded stone aggregates Without flyash in all types of concrete works such as footings, columns, pedestals, rafts, beams, lofts, slabs, walls, lintels, chajjas, canopies, facias, fins, bands, shelves, staircases, pits, chambers, rain water chutes, gutt­ers, pardi, curbs, pipe racks, & equipment foundations, etc. of square, rectangular, hexagonal, octagonal and circular shapes including leaving pockets, openings in slabs, vibrating, tamping, finishing, curing and rendering if required, etc. complete as per drawings and specifications but excluding the cost of formwork and reinforcement. Cement: OPC53 grade Ultra tech, Ambuja Supply of cement will be in contractor's scope. Mix Design has to be approved from Consultant.
A52: B-02 A1 | B52: In foundations and up to plinths (FFL) at all depths:
B53: a) M: 20 Grade (min . Cement : 300 kg/m3) | D53: Cu.m | E53: 5450
B54: b) M: 25 Grade (min . Cement : 340 kg/m3) | D54: Cu.m | E54: 5850 | F54: =E54*C54 -> 0
B55: c) Extra for M30 Concrete in place of M25 (Min. Cement- 370 KG/M3) | D55: Cu.m | E55: 950
A56: B-02 A2 | B56: In superstructure above finished floor level at all heights.
B57: a) M : 20 Grade
B58: i) From FFL up to + 5.5M lvl. | D58: Cu.m | E58: 5700 | F58: =E58*C58 -> 0
B59: ii) Above + 5.5M lvl. | D59: Cu.m
B60: b) M : 25 Grade
B61: i) From FFL up to + 5.5M lvl. | D61: Cu.m | E61: 5900 | F61: =E61*C61 -> 0
B62: ii) Above + 5.5M lvl up to + 11.0M lvl | D62: Cu.m | E62: 6650
B63: c) Extra for M30 Concrete in place of M25 (Min. Cement- 370 KG/M3) | D63: Cu.m | E63: 950
A64: B-02B | B64: Providing and laying reinforced cement concrete with 20mm and down size graded stone aggregates in PILE. of circular shapes including tamping, curing and development of pile- including use of trimi, breaking (Upto 0.60m length), cleanning etc. complete as per drawings and specifications but excluding the cost of formwork and reinforcement. (USE GRADE OF CONC. M25)
B65: (a) For 250mm dia. Pile | D65: CUM | E65: 5600
B66: (b) For 300mm dia. Pile | D66: CUM | E66: 5369 | F66: =E66*C66 -> 0
B67: (b) For 350mm dia. Pile | C67: 4 | D67: CUM | E67: 5650 | F67: =E67*C67 -> 22600
B68: (c) For 400mm dia. Pile | D68: CUM | E68: 5650 | F68: =E68*C68 -> 0
A69: B-02C | B69: Providing and laying reinforced cement concrete with 20mm and down size graded stone aggregates in PRECAST concrete works for storm water trench, Chamber Cover etc. of square, rectangular, hexagonal, octagonal and circular shapes including leaving pockets, openings in covers, vibrating, tamping, finishing, curing and rendering if required, etc. complete as per drawings and specifications. The rate includes the cost of formwork and installing the elements in line and level. (Reinforcement steel is paid seperately in item no. B-05 )
B70: (a) M25 grade | D70: CUM | E70: 9500
B71: (b) M30 grade | D71: CUM | E71: 9500
A72: B-02D | B72: Providing and laying M25 Grade Reinforced cement concrete for water retaining structures/Cable Trech / basement structures/over head tanks, ETP, scale pit, basins sumps / sump pits, manholes, inspection chambers of sewage / drainage lines etc at any level and location. Including addition of water proofing compound WAREP 1000L Manufactured by Thermax Ltd. , FOSROC-CONPLAST '-X4211C- or equivalent approved make in concrete as per approved manufacturer's specification, including pressure cement grouting of mix 1:1 with water proofing additives MAXGROUT 100 MANUFACTURED by THERMAX LTD.or equivalent at construction joints, weak spot / honey combs and testing the same for water tightness as per requirements of IS 3370 and making good defects / leakages as instructed by Engineers / Owners. Rate also to include cost of water proofing compound, testing and rectification of leakage etc
B73: a) M: 25 Grade (Minimum Cement : 340 kg/M3)
B74: 1. In foundations and up to plinths (FFL) at all depths: | D74: CUM | E74: 5750 | F74: =E74*C74 -> 0
B75: i) From FFL up to + 5.5 M lvl. | D75: CUM | E75: 6650
B76: ii) Above + 5.5M lvl up to + 11.0 M lvl | D76: CUM | E76: 6850
B77: ii) Above + 11.0M lvl up to + 16.5M lvl | D77: CUM | E77: 7250
A78: B-03 | B78: For addition of approved quality plasticiser as directed and specified by the engineer incharge (BASF or SIKA make only)
B79: a) For early de shuttering (basic rate:90 Rs/Ltr.) | D79: LTRS | E79: 175 | F79: =E79*C79 -> 0
A80: B-04 | B80: Providing, fabricating, laying and fixing in position reinforcement for all type of RCC works at all levels, including cost of straightening, cutting, bending to required shape, binding with 16 gauge MS annealed binding wire, spacer blocks of cement mortar 1:2 with embedded binding wire of appropriate length, etc. complete as per drawings and specifications [Chairs, pins will not be measured and paid extra. Only authorized laps shall be measured and paid for] Note:- HYSD reinforcements (Fe500) of make "HY-TUF" , "Electro therm" or "ISPAT"
B81: a) High yield strength deformed bars | C81: 1.5 | D81: MT | E81: 69500 | F81: =E81*C81 -> 104250
A82: B-05 | B82: Providing and fixing form work including necessary centering for footings, columns, pedestals, rafts, blocks, walls, beams, slabs, copings, pipe supports, equipment foundations, floors, roads, water retaining structures / any type of structural members etc. of any shapes including strutting, bracing, shoring, propping, staging, etc. keeping the same in position during concreting and removal of the same after a specified period, including smooth rendering of concrete surface if required, complete as per drawings and specifications (Rate to include coating formwork with approved quality of non-staining mineral oil).
B83: 1. In foundations and up to plinths (FFL) at all depths: | C83: 25 | D83: SQM | E83: 550 | F83: =C83*E83 -> 13750
B84: i) From FFL up to + 5.5 M lvl. | D84: SQM | E84: 625
A85: B-06 | B85: Providing and fixing plywood form work including necessary centering for alignment and levels for columns, blocks, pedestals, lintels, beams (regular and inverted), slabs, chajjas, copings, gutters, pardi, facias, fins, bands, walls, staircases, slopping RCC elements, rain water chutes, etc. of rectangular, square shapes, curve, including strutting, shoring, bracing, propping, staging, water retaining structure / any type of structure member, etc. keeping the same in position during the concreting and removal of the same after a specified period, etc. complete as per drawings and specifications. The framework shall ensure smooth finish surface without any additional rendering. Rate to include coating formwork with approved quality of non-staining mineral oil.
B86: 1. In foundations and up to plinths (FFL) at all depths: | D86: SQM | E86: 575
B87: i) From FFL up to + 5.5 M lvl. | C87: 58 | D87: SQM | E87: 650 | F87: =E87*C87 -> 37700
B88: ii) Above + 5.5M lvl up to + 11.0 M lvl | D88: SQM | E88: 725
B89: ii) Above + 11.0 M lvl up to + 16.5 M lvl | D89: SQM | E89: 850
A90: B-08 | B90: Providing free flow grouting under base plates and in pockets for holding down in pockets with GP2 of approved make including formwork, finishing, curing, etc. complete as directed by the Engineer. | D90: CUM | E90: 52500 | F90: =E90*C90 -> 0
A91: B-09 | B91: Providing and doing welding continuous or intermittent using 4.2mm welding rod in line & removing slag etc. complete.(only welding length shall be considered for mesurment.) | D91: RMT | E91: 550
A92: B-11 | B92: Providing and fixing in position in PCC/RCC work at all levels, shuttering for pockets of varying sizes as per details with necessary form work including type of form work where required and carefully removing the same for anchor and holding down bolts for columns, pedestals, pipe rack, equipment foundations, etc. all as per detailed drawing / as directed by the Engineer.
B93: a) For pocket area up to 0.01 Sq.m. and depth up to 0.30M | D93: Nos. | E93: 800 | F93: =E93*C93 -> 0
B94: b) For pocket area above 0.01 Sq.m. up to 0.03 Sq.m. and depth up to 0.30M | D94: Nos. | E94: 1050 | F94: =E94*C94 -> 0
B95: c) For pocket area above 0.03 Sq.m. up to 0.05 Sq.m. and depth up to 0.60M | D95: Nos. | E95: 1250 | F95: =E95*C95 -> 0
B96: d) For pocket area up to 0.01 Sq.m. and depth up to 0.75M | D96: Nos. | E96: 1250 | F96: =E96*C96 -> 0
B97: e) For pocket area above 0.01 Sq.m. up to 0.03 Sq.m. and depth up to 0.75M | D97: Nos. | E97: 1350 | F97: =E97*C97 -> 0
B98: f) For pocket area above 0.03 Sq.m. up to 0.05 Sq.m. and depth up to 1.0M | D98: Nos. | E98: 2000 | F98: =E98*C98 -> 0
B99: g) For pocket area up to 0.01 Sq.m. and depth up to 1.25M | D99: Nos. | E99: 1950 | F99: =E99*C99 -> 0
B100: h) For pocket area above 0.01 Sq.m. up to 0.03 Sq.m. and depth up to 1.25M | D100: Nos. | E100: 2250 | F100: =E100*C100 -> 0
...

Sheet BOQ -COOLING TOWER 
B1: ESTIMATED BOQ FOR PROPOSED COOLING TOWER CIVIL & STRUCTURAL WORKS For SUYOG ELECTRICAL LTD. NO 245/33/B,245/55/B/2,MOJE BODIDARA, TA.VADODARA, GUJARAT, INDIA.
A2: Followings are the scope of work: - COOLING TOWER Civil and Structural works (Excluding PEB shed) - Approximately 500 TR - 2nos -
A3: BOQ
A4: Sr. No. | B4: Description | C4: QTY. | D4: UNIT | E4: RATE | F4: AMOUNT
B5: SECTION- A EARTH WORK AND SOLING
A6: A-01 | B6: Cleaning the area by grass cutting, removing vegetations,roots of trees if any, scraping the existing surfaces up to 150mm, removal of all loose materials and other matters, etc. and disposing off the debris beyond the plant boundary as directed by the Engineer. | C6: 109 | D6: SQ.M. | E6: 35 | F6: =E6*C6 -> 3815
A7: A-01A | B7: Clearing the area by jungle cutting, removing trees / bushes if any from roots, scraping the existing surfaces up to 150mm, removal of all loose materials and other matters, etc. and disposing off the debris beyond the plant boundary as directed by EIC. | D7: SQ.M. | E7: 25 | F7: =E7*C7 -> 0
A8: A-02 | B8: Earth work excavation for all type of work in all soils like black cotton soil, clay, sand, soft and hard murrum, etc. but other than soft and hard rock including shoring, strutting and dewatering due to any sub soil water, rain water or any reason if required and refilling in foundations with selected excavated earth in 350mm layers, watering and consolidating to 250mm thickness, disposing off surplus excavated materials within the plant boundary at selected places, spreading evenly, leveling, etc. complete as per specifications and as directed. (Payment shall be made for 300mm from R.C.C. face for foundations and 200mm from R.C.C. face for GB)
B9: a) From average ground level up to 1.50M depth. | C9: 14 | D9: CUM | E9: 250 | F9: =E9*C9 -> 3500
B10: b) Below 1.5M up to 3M depth | D10: CUM | E10: 285 | F10: =E10*C10 -> 0
B11: c) Below 3.0M up to 4.5M depth | D11: CUM | E11: 350
B12: d) Below 4.5M up to 6.0M depth | D12: CUM | E12: 450
B13: e) Below 6.0M up to 7.5M depth | D13: CUM | E13: 575
A14: A-03 | B14: Filling in plinth & foundation pits with approved materials including spreading in 150mm layers, watering, ramming, compacting with 10MT vibro/static roller or portable compactor wherever applicable as decided by the Engineer, leveling, etc. complete. (Measurements for compacted volume is considered)
B15: a) With selected earth brought from outside | C15: 16 | D15: CUM | E15: 490 | F15: =E15*C15 -> 7840
B16: b) With approved filling sand brought from Outside. | C16: 16 | D16: CUM | E16: 1025 | F16: =E16*C16 -> 16400
B17: c) Approved quarry dust filling | D17: CUM | E17: 1150
A18: A-04 | B18: Disposing off surplus excavated materials by carting away, outside of company premises at location decided by contractor and shall be responsibility of contractor | D18: CUM | E18: 150 | F18: =E18*C18 -> 0
A19: A-04A | B19: Disposing off dumped Earth / Debris by carting away, outside of company premises at location decided by contractor and shall be responsibility of contractor
B20: a) Measurement of available material by volume | D20: CUM | E20: 100 | F20: =E20*C20 -> 0
B21: b) Measurement of available material by Dumper | D21: Nos. | E21: 3500
A22: A-05 | B22: Providing and laying black trap rubble soling at required level and grade in foundations, in plinth, ramps, etc. including hand packing, filling interstices with quarry / sand, watering and compacting with suitable vibro roller/ Static roller or earth compactor wherever applicable as decided by the Engineer to the consolidated thickness as stated below:
B23: i) 230mm thick Soling | D23: SQ.M | E23: 517
B24: ii) 150mm thick compacted layer metal packing using 63-90 mm size hand broken stone etc. as directed Engineer in charge/consultant. | C24: 76 | D24: SQ.M | E24: 310 | F24: =E24*C24 -> 23560
B25: iii) 75mm thick compacted layer metal packing using 40-63 mm size hand broken stone etc. as directed Engineer in charge/consultant. | C25: 76 | D25: SQ.M | E25: 150 | F25: =E25*C25 -> 11400
A26: A-06 | B26: Auguring(Upto 8m depth) of under ream pile foundation work in all sorts of soil viz. sand, clay, soft & hard murrum for execution of the above work. Contractor has to brought all necessary tools, tackles, equipments, manpower & supervision. Items also include carting of debris/soil, unloading, stacking, use of bentonite, spreading, levelling, compacting, consolidating surplus marterial within company premises, dewatering & one bulb as per design etc. complete as directed
B27: (a) For 250mm dia. Pile | D27: RM | E27: 300
B28: (b) For 300mm dia. Pile | D28: RM | E28: 350 | F28: =E28*C28 -> 0
B29: (c) For 350mm dia. Pile | D29: RM | E29: 425 | F29: =E29*C29 -> 0
B30: (d) For 400mm dia. Pile | D30: RM | E30: 495 | F30: =E30*C30 -> 0
B31: (e) For 450mm dia. Pile | C31: 77 | D31: RM | E31: 500 | F31: =E31*C31 -> 38500
A32: A-07 | B32: -do- as per item no. A-06 but for construction of extra bulb in the pile at any level. The size of the bulb will be as per design.
B33: (a) For 250mm dia. Pile | D33: NO | E33: 300
B34: (b) For 300mm dia. Pile | D34: NO | E34: 400
B35: (c) For 350mm dia. Pile | D35: NO | E35: 450
B36: (d) For 400mm dia. Pile | D36: NO | E36: 500
B37: TOTAL OF SECTION `A` | F37: =SUM(F6:F36) -> 105015
B38: SECTION - B CONCRETE
A39: B-01 | B39: Providing and laying Plain cement concrete below all R.C.C. member, floors, ramps, chembers etc. with 20mm nominal size graded stone aggregates of approved quality (black trap only) including leveling, compacting, curing and form work if any, etc. complete.
B40: a) Mix 1: 4: 8 | C40: 2 | D40: CUM | E40: 4100 | F40: =E40*C40 -> 8200
B41: b) Mix 1: 3: 6 | D41: CUM | E41: 4175 | F41: =E41*C41 -> 0
A42: B-02 | B42: Providing and laying reinforced cement concrete with 20mm and down size graded stone aggregates in all types of concrete works such as footings, columns, pedestals, rafts, beams, lofts, slabs, walls, lintels, chajjas, canopies, facias, fins, bands, shelves, staircases, all other any type of structural members, pits, chambers, rain water chutes, gutters, pardi, curbs, pipe racks, & equipment foundations, etc. of square, rectangular, hexagonal, octagonal and circular shapes including leaving pockets, vatas, openings in slabs, including vibrating, tamping, finishing, curing and rendering if required, etc. complete as per drawings and specifications but excluding the cost of formwork and reinforcement. (No false staging shall be given.) Cement Make: Ultratech / JK Lakshmi / Ambuja - OPC 53 grade (Applicable to all items)
B43: a) M : 20 Grade (Min. Cement - 300 KG/M3)
B44: 1. In foundations and up to plinths (FFL) at all depths: | D44: CUM | E44: 5450 | F44: =E44*C44 -> 0
B45: i) From FFL up to + 5.5 M lvl. | D45: CUM | E45: 5950 | F45: =E45*C45 -> 0
B46: b) M: 25 Grade (Min. Cement - 340 KG/M3)
B47: 1. In foundations and up to plinths (FFL) at all depths: | C47: 21 | D47: CUM | E47: 5850 | F47: =E47*C47 -> 122850
B48: i) From FFL up to + 5.0 M lvl. | C48: 57 | D48: CUM | E48: 6175 | F48: =E48*C48 -> 351975
B49: ii) Above + 5.0M lvl up to + 11.0 M lvl | D49: CUM | E49: 6350 | F49: =E49*C49 -> 0
B50: c) Extra for M30 Concrete in place of M25 (Min. Cement- 370 KG/M3) | D50: CUM | E50: 950 | F50: =E50*C50 -> 0
A51: B-02A | B51: Ready Mix Concreate (Prior Permission shall be taken before using Ready Mix Concrete from engineer Incharge)
B52: Providing and laying ready mix concrete with 20mm and down size graded stone aggregates Without flyash in all types of concrete works such as footings, columns, pedestals, rafts, beams, lofts, slabs, walls, lintels, chajjas, canopies, facias, fins, bands, shelves, staircases, pits, chambers, rain water chutes, gutt­ers, pardi, curbs, pipe racks, & equipment foundations, etc. of square, rectangular, hexagonal, octagonal and circular shapes including leaving pockets, openings in slabs, vibrating, tamping, finishing, curing and rendering if required, etc. complete as per drawings and specifications but excluding the cost of formwork and reinforcement. Cement: OPC53 grade Ultra tech, Ambuja Supply of cement will be in contractor's scope. Mix Design has to be approved from Consultant.
A53: B-02 A1 | B53: In foundations and up to plinths (FFL) at all depths:
B54: a) M: 20 Grade (min . Cement : 300 kg/m3) | D54: Cu.m | E54: 5450 | F54: =E54*C54 -> 0
B55: b) M: 25 Grade (min . Cement : 340 kg/m3) | D55: Cu.m | E55: 5850 | F55: =E55*C55 -> 0
B56: c) Extra for M30 Concrete in place of M25 (Min. Cement- 370 KG/M3) | D56: Cu.m | E56: 950 | F56: =E56*C56 -> 0
A57: B-02 A2 | B57: In superstructure above finished floor level at all heights.
B58: a) M : 20 Grade
B59: i) From FFL up to + 5.5M lvl. | D59: Cu.m | E59: 5700 | F59: =E60*C59 -> 0
B60: ii) Above + 5.5M lvl. | D60: Cu.m
B61: b) M : 25 Grade
B62: i) From FFL up to + 5.5M lvl. | D62: Cu.m | E62: 5900 | F62: =E62*C62 -> 0
B63: ii) Above + 5.5M lvl up to + 11.0M lvl | D63: Cu.m | E63: 6650 | F63: =E63*C63 -> 0
B64: c) Extra for M30 Concrete in place of M25 (Min. Cement- 370 KG/M3) | D64: Cu.m | E64: 950 | F64: =E64*C64 -> 0
A65: B-02B | B65: Providing and laying reinforced cement concrete with 20mm and down size graded stone aggregates in PILE. of circular shapes including tamping, curing and development of pile- including use of trimi, breaking (Upto 0.60m length), cleanning etc. complete as per drawings and specifications but excluding the cost of formwork and reinforcement. (USE GRADE OF CONC. M25)
B66: (a) For 250mm dia. Pile | D66: CUM | E66: 5600 | F66: =E66*C66 -> 0
B67: (b) For 300mm dia. Pile | D67: CUM | E67: 5369 | F67: =E67*C67 -> 0
B68: (b) For 350mm dia. Pile | D68: CUM | E68: 5650 | F68: =E68*C68 -> 0
B69: (c) For 400mm dia. Pile | D69: CUM | E69: 5650 | F69: =E69*C69 -> 0
B70: (d) For 450mm dia. Pile | C70: 13 | D70: CUM | E70: 5650 | F70: =E70*C70 -> 73450
A71: B-02C | B71: Providing and laying reinforced cement concrete with 20mm and down size graded stone aggregates in PRECAST concrete works for storm water trench, Chamber Cover etc. of square, rectangular, hexagonal, octagonal and circular shapes including leaving pockets, openings in covers, vibrating, tamping, finishing, curing and rendering if required, etc. complete as per drawings and specifications. The rate includes the cost of formwork and installing the elements in line and level. (Reinforcement steel is paid seperately in item no. B-05 ) | E71: 9500
B72: (a) M25 grade | D72: CUM | E72: 9500 | F72: =E72*C72 -> 0
B73: (b) M30 grade | D73: CUM | F73: =E73*C73 -> 0
A74: B-02D | B74: Providing and laying M25 Grade Reinforced cement concrete for water retaining structures/Cable Trech / basement structures/over head tanks, ETP, scale pit, basins sumps / sump pits, manholes, inspection chambers of sewage / drainage lines etc at any level and location. Including addition of water proofing compound WAREP 1000L Manufactured by Thermax Ltd. , FOSROC-CONPLAST '-X4211C- or equivalent approved make in concrete as per approved manufacturer's specification, including pressure cement grouting of mix 1:1 with water proofing additives MAXGROUT 100 MANUFACTURED by THERMAX LTD.or equivalent at construction joints, weak spot / honey combs and testing the same for water tightness as per requirements of IS 3370 and making good defects / leakages as instructed by Engineers / Owners. Rate also to include cost of water proofing compound, testing and rectification of leakage etc
B75: a) M: 25 Grade (Minimum Cement : 340 kg/M3)
B76: 1. In foundations and up to plinths (FFL) at all depths: | D76: CUM | E76: 5750 | F76: =E76*C76 -> 0
B77: i) From FFL up to + 5.5 M lvl. | D77: CUM | E77: 6650 | F77: =E77*C77 -> 0
B78: ii) Above + 5.5M lvl up to + 11.0 M lvl | D78: CUM | E78: 6850 | F78: =E78*C78 -> 0
B79: ii) Above + 11.0M lvl up to + 16.5M lvl | D79: CUM | E79: 7250 | F79: =E79*C79 -> 0
A80: B-03 | B80: For addition of approved quality plasticiser as directed and specified by the engineer incharge (BASF or SIKA make only)
B81: a) For early de shuttering (basic rate:90 Rs/Ltr.) | D81: LTRS | E81: 175 | F81: =E81*C81 -> 0
A82: B-04 | B82: Providing, fabricating, laying and fixing in position reinforcement for all type of RCC works at all levels, including cost of straightening, cutting, bending to required shape, binding with 16 gauge MS annealed binding wire, spacer blocks of cement mortar 1:2 with embedded binding wire of appropriate length, etc. complete as per drawings and specifications [Chairs, pins will not be measured and paid extra. Only authorized laps shall be measured and paid for] Note:- HYSD reinforcements (Fe500) of make "HY-TUF" , "Electro therm" or "ISPAT"
B83: a) High yield strength deformed bars | C83: 11 | D83: MT | E83: 69500 | F83: =E83*C83 -> 764500
A84: B-05 | B84: Providing and fixing form work including necessary centering for footings, columns, pedestals, rafts, blocks, walls, beams, slabs, copings, pipe supports, equipment foundations, floors, roads, water retaining structures / any type of structural members etc. of any shapes including strutting, bracing, shoring, propping, staging, etc. keeping the same in position during concreting and removal of the same after a specified period, including smooth rendering of concrete surface if required, complete as per drawings and specifications (Rate to include coating formwork with approved quality of non-staining mineral oil).
B85: 1. In foundations and up to plinths (FFL) at all depths: | C85: 100 | D85: SQM | E85: 550 | F85: =E85*C85 -> 55000
B86: i) From FFL up to + 5.5 M lvl. | C86: 395 | D86: SQM | E86: 625 | F86: =E86*C86 -> 246875
A87: B-06 | B87: Providing and fixing plywood form work including necessary centering for alignment and levels for columns, blocks, pedestals, lintels, beams (regular and inverted), slabs, chajjas, copings, gutters, pardi, facias, fins, bands, walls, staircases, slopping RCC elements, rain water chutes, etc. of rectangular, square shapes, curve, including strutting, shoring, bracing, propping, staging, water retaining structure / any type of structure member, etc. keeping the same in position during the concreting and removal of the same after a specified period, etc. complete as per drawings and specifications. The framework shall ensure smooth finish surface without any additional rendering. Rate to include coating formwork with approved quality of non-staining mineral oil.
B88: 1. In foundations and up to plinths (FFL) at all depths: | D88: SQM | E88: 575 | F88: =E88*C88 -> 0
B89: i) From FFL up to + 5.5 M lvl. | D89: SQM | E89: 650 | F89: =E89*C89 -> 0
B90: ii) Above + 5.5M lvl up to + 11.0 M lvl | D90: SQM | E90: 725 | F90: =E90*C90 -> 0
B91: ii) Above + 11.0 M lvl up to + 16.5 M lvl | D91: SQM | E91: 850 | F91: =E91*C91 -> 0
A92: B-08 | B92: Providing free flow grouting under base plates and in pockets for holding down in pockets with GP2 of approved make including formwork, finishing, curing, etc. complete as directed by the Engineer. | C92: 1 | D92: CUM | E92: 52500 | F92: =E92*C92 -> 52500
A93: B-09 | B93: Providing and doing welding continuous or intermittent using 4.2mm welding rod in line & removing slag etc. complete.(only welding length shall be considered for mesurment.) | D93: RMT | E93: 550
A94: B-11 | B94: Providing and fixing in position in PCC/RCC work at all levels, shuttering for pockets of varying sizes as per details with necessary form work including type of form work where required and carefully removing the same for anchor and holding down bolts for columns, pedestals, pipe rack, equipment foundations, etc. all as per detailed drawing / as directed by the Engineer.
B95: a) For pocket area up to 0.01 Sq.m. and depth up to 0.30M | D95: Nos. | E95: 800 | F95: =E96*C95 -> 0
B96: b) For pocket area above 0.01 Sq.m. up to 0.03 Sq.m. and depth up to 0.30M | D96: Nos. | E96: 1050 | F96: =E97*C96 -> 0
B97: c) For pocket area above 0.03 Sq.m. up to 0.05 Sq.m. and depth up to 0.60M | D97: Nos. | E97: 1250 | F97: =E98*C97 -> 0
B98: d) For pocket area up to 0.01 Sq.m. and depth up to 0.75M | D98: Nos. | E98: 1250 | F98: =E99*C98 -> 0
B99: e) For pocket area above 0.01 Sq.m. up to 0.03 Sq.m. and depth up to 0.75M | D99: Nos. | E99: 1350 | F99: =E100*C99 -> 0
B100: f) For pocket area above 0.03 Sq.m. up to 0.05 Sq.m. and depth up to 1.0M | D100: Nos. | E100: 2000 | F100: =E101*C100 -> 0
...

Sheet BOQ -WEIGH BRIDGE 
B1: ESTIMATED BOQ FOR PROPOSED WEIGH BRIDGE CIVIL & STRUCTURAL WORKS For SUYOG ELECTRICAL LTD. NO 245/33/B,245/55/B/2,MOJE BODIDARA, TA.VADODARA, GUJARAT, INDIA.
A2: Followings are the scope of work: - 100 TON WEIGH BRIDGE Civil and Structural works (Excluding PEB shed) - Approximately 100 TON -
A3: BOQ
A4: Sr. No. | B4: Description | C4: QTY. | D4: UNIT | E4: RATE | F4: AMOUNT
B5: SECTION- A EARTH WORK AND SOLING
A6: A-01 | B6: Cleaning the area by grass cutting, removing vegetations,roots of trees if any, scraping the existing surfaces up to 150mm, removal of all loose materials and other matters, etc. and disposing off the debris beyond the plant boundary as directed by the Engineer. | C6: 87 | D6: SQ.M. | E6: 35 | F6: =E6*C6 -> 3045
A7: A-01A | B7: Clearing the area by jungle cutting, removing trees / bushes if any from roots, scraping the existing surfaces up to 150mm, removal of all loose materials and other matters, etc. and disposing off the debris beyond the plant boundary as directed by EIC. | D7: SQ.M. | E7: 25 | F7: =E7*C7 -> 0
A8: A-02 | B8: Earth work excavation for all type of work in all soils like black cotton soil, clay, sand, soft and hard murrum, etc. but other than soft and hard rock including shoring, strutting and dewatering due to any sub soil water, rain water or any reason if required and refilling in foundations with selected excavated earth in 350mm layers, watering and consolidating to 250mm thickness, disposing off surplus excavated materials within the plant boundary at selected places, spreading evenly, leveling, etc. complete as per specifications and as directed. (Payment shall be made for 300mm from R.C.C. face for foundations and 200mm from R.C.C. face for GB)
B9: a) From average ground level up to 1.50M depth. | C9: 168 | D9: CUM | E9: 250 | F9: =E9*C9 -> 42000
B10: b) Below 1.5M up to 3M depth | C10: 42 | D10: CUM | E10: 285 | F10: =E10*C10 -> 11970
B11: c) Below 3.0M up to 4.5M depth | D11: CUM | E11: 350
B12: d) Below 4.5M up to 6.0M depth | D12: CUM | E12: 450
B13: e) Below 6.0M up to 7.5M depth | D13: CUM | E13: 575
A14: A-03 | B14: Filling in plinth & foundation pits with approved materials including spreading in 150mm layers, watering, ramming, compacting with 10MT vibro/static roller or portable compactor wherever applicable as decided by the Engineer, leveling, etc. complete. (Measurements for compacted volume is considered)
B15: a) With selected earth brought from outside | C15: 5 | D15: CUM | E15: 490 | F15: =E15*C15 -> 2450
B16: b) With approved filling sand brought from Outside. | C16: 21 | D16: CUM | E16: 1025 | F16: =E16*C16 -> 21525
B17: c) Approved quarry dust filling | D17: CUM | E17: 1150
A18: A-04 | B18: Disposing off surplus excavated materials by carting away, outside of company premises at location decided by contractor and shall be responsibility of contractor | C18: 187 | D18: CUM | E18: 150 | F18: =E18*C18 -> 28050
A19: A-04A | B19: Disposing off dumped Earth / Debris by carting away, outside of company premises at location decided by contractor and shall be responsibility of contractor
B20: a) Measurement of available material by volume | D20: CUM | E20: 100 | F20: =E20*C20 -> 0
B21: b) Measurement of available material by Dumper | D21: Nos. | E21: 3500
A22: A-05 | B22: Providing and laying black trap rubble soling at required level and grade in foundations, in plinth, ramps, etc. including hand packing, filling interstices with quarry / sand, watering and compacting with suitable vibro roller/ Static roller or earth compactor wherever applicable as decided by the Engineer to the consolidated thickness as stated below:
B23: i) 230mm thick Soling | D23: SQ.M | E23: 517
B24: ii) 150mm thick compacted layer metal packing using 63-90 mm size hand broken stone etc. as directed Engineer in charge/consultant. | C24: 116 | D24: SQ.M | E24: 310 | F24: =E24*C24 -> 35960
B25: iii) 75mm thick compacted layer metal packing using 40-63 mm size hand broken stone etc. as directed Engineer in charge/consultant. | D25: SQ.M | E25: 150 | F25: =E25*C25 -> 0
A26: A-06 | B26: Auguring(Upto 8m depth) of under ream pile foundation work in all sorts of soil viz. sand, clay, soft & hard murrum for execution of the above work. Contractor has to brought all necessary tools, tackles, equipments, manpower & supervision. Items also include carting of debris/soil, unloading, stacking, use of bentonite, spreading, levelling, compacting, consolidating surplus marterial within company premises, dewatering & one bulb as per design etc. complete as directed
B27: (a) For 250mm dia. Pile | D27: RM | E27: 300
B28: (b) For 300mm dia. Pile | D28: RM | E28: 350 | F28: =E28*C28 -> 0
B29: (c) For 350mm dia. Pile | D29: RM | E29: 425 | F29: =E29*C29 -> 0
B30: (d) For 400mm dia. Pile | D30: RM | E30: 495 | F30: =E30*C30 -> 0
A31: A-07 | B31: -do- as per item no. A-06 but for construction of extra bulb in the pile at any level. The size of the bulb will be as per design.
B32: (a) For 250mm dia. Pile | D32: NO | E32: 300
B33: (b) For 300mm dia. Pile | D33: NO | E33: 400
B34: (c) For 350mm dia. Pile | D34: NO | E34: 450
B35: (d) For 400mm dia. Pile | D35: NO | E35: 500
B36: TOTAL OF SECTION `A` | F36: =SUM(F6:F35) -> 145000
B37: SECTION - B CONCRETE
A38: B-01 | B38: Providing and laying Plain cement concrete below all R.C.C. member, floors, ramps, chembers etc. with 20mm nominal size graded stone aggregates of approved quality (black trap only) including leveling, compacting, curing and form work if any, etc. complete.
B39: a) Mix 1: 4: 8 | C39: 10 | D39: CUM | E39: 4100 | F39: =E39*C39 -> 41000
B40: b) Mix 1: 3: 6 | D40: CUM | E40: 4175 | F40: =E40*C40 -> 0
A41: B-02 | B41: Providing and laying reinforced cement concrete with 20mm and down size graded stone aggregates in all types of concrete works such as footings, columns, pedestals, rafts, beams, lofts, slabs, walls, lintels, chajjas, canopies, facias, fins, bands, shelves, staircases, all other any type of structural members, pits, chambers, rain water chutes, gutters, pardi, curbs, pipe racks, & equipment foundations, etc. of square, rectangular, hexagonal, octagonal and circular shapes including leaving pockets, vatas, openings in slabs, including vibrating, tamping, finishing, curing and rendering if required, etc. complete as per drawings and specifications but excluding the cost of formwork and reinforcement. (No false staging shall be given.) Cement Make: Ultratech / JK Lakshmi / Ambuja - OPC 53 grade (Applicable to all items)
B42: a) M : 20 Grade (Min. Cement - 300 KG/M3)
B43: 1. In foundations and up to plinths (FFL) at all depths: | D43: CUM | E43: 5450
B44: i) From FFL up to + 5.5 M lvl. | D44: CUM | E44: 5950
B45: b) M: 25 Grade (Min. Cement - 340 KG/M3)
B46: 1. In foundations and up to plinths (FFL) at all depths: | C46: 29 | D46: CUM | E46: 5850 | F46: =E46*C46 -> 169650
B47: i) From FFL up to + 5.0 M lvl. | D47: CUM | E47: 6175 | F47: =E47*C47 -> 0
B48: ii) Above + 5.0M lvl up to + 11.0 M lvl | D48: CUM | E48: 6350
B49: c) Extra for M30 Concrete in place of M25 (Min. Cement- 370 KG/M3) | D49: CUM | E49: 950
A50: B-02A | B50: Ready Mix Concreate (Prior Permission shall be taken before using Ready Mix Concrete from engineer Incharge)
B51: Providing and laying ready mix concrete with 20mm and down size graded stone aggregates Without flyash in all types of concrete works such as footings, columns, pedestals, rafts, beams, lofts, slabs, walls, lintels, chajjas, canopies, facias, fins, bands, shelves, staircases, pits, chambers, rain water chutes, gutt­ers, pardi, curbs, pipe racks, & equipment foundations, etc. of square, rectangular, hexagonal, octagonal and circular shapes including leaving pockets, openings in slabs, vibrating, tamping, finishing, curing and rendering if required, etc. complete as per drawings and specifications but excluding the cost of formwork and reinforcement. Cement: OPC53 grade Ultra tech, Ambuja Supply of cement will be in contractor's scope. Mix Design has to be approved from Consultant.
A52: B-02 A1 | B52: In foundations and up to plinths (FFL) at all depths:
B53: a) M: 20 Grade (min . Cement : 300 kg/m3) | D53: Cu.m | E53: 5450
B54: b) M: 25 Grade (min . Cement : 340 kg/m3) | D54: Cu.m | E54: 5850 | F54: =E54*C54 -> 0
B55: c) Extra for M30 Concrete in place of M25 (Min. Cement- 370 KG/M3) | D55: Cu.m | E55: 950
A56: B-02 A2 | B56: In superstructure above finished floor level at all heights.
B57: a) M : 20 Grade
B58: i) From FFL up to + 5.5M lvl. | D58: Cu.m | E58: 5700 | F58: =E58*C58 -> 0
B59: ii) Above + 5.5M lvl. | D59: Cu.m
B60: b) M : 25 Grade
B61: i) From FFL up to + 5.5M lvl. | D61: Cu.m | E61: 5900 | F61: =E61*C61 -> 0
B62: ii) Above + 5.5M lvl up to + 11.0M lvl | D62: Cu.m | E62: 6650
B63: c) Extra for M30 Concrete in place of M25 (Min. Cement- 370 KG/M3) | D63: Cu.m | E63: 950
A64: B-02B | B64: Providing and laying reinforced cement concrete with 20mm and down size graded stone aggregates in PILE. of circular shapes including tamping, curing and development of pile- including use of trimi, breaking (Upto 0.60m length), cleanning etc. complete as per drawings and specifications but excluding the cost of formwork and reinforcement. (USE GRADE OF CONC. M25)
B65: (a) For 250mm dia. Pile | D65: CUM | E65: 5600
B66: (b) For 300mm dia. Pile | D66: CUM | E66: 5369 | F66: =E66*C66 -> 0
B67: (b) For 350mm dia. Pile | D67: CUM | E67: 5650 | F67: =E67*C67 -> 0
B68: (c) For 400mm dia. Pile | D68: CUM | E68: 5650 | F68: =E68*C68 -> 0
A69: B-02C | B69: Providing and laying reinforced cement concrete with 20mm and down size graded stone aggregates in PRECAST concrete works for storm water trench, Chamber Cover etc. of square, rectangular, hexagonal, octagonal and circular shapes including leaving pockets, openings in covers, vibrating, tamping, finishing, curing and rendering if required, etc. complete as per drawings and specifications. The rate includes the cost of formwork and installing the elements in line and level. (Reinforcement steel is paid seperately in item no. B-05 )
B70: (a) M25 grade | D70: CUM | E70: 9500
B71: (b) M30 grade | D71: CUM | E71: 9500
A72: B-02D | B72: Providing and laying M25 Grade Reinforced cement concrete for water retaining structures/Cable Trech / basement structures/over head tanks, ETP, scale pit, basins sumps / sump pits, manholes, inspection chambers of sewage / drainage lines etc at any level and location. Including addition of water proofing compound WAREP 1000L Manufactured by Thermax Ltd. , FOSROC-CONPLAST '-X4211C- or equivalent approved make in concrete as per approved manufacturer's specification, including pressure cement grouting of mix 1:1 with water proofing additives MAXGROUT 100 MANUFACTURED by THERMAX LTD.or equivalent at construction joints, weak spot / honey combs and testing the same for water tightness as per requirements of IS 3370 and making good defects / leakages as instructed by Engineers / Owners. Rate also to include cost of water proofing compound, testing and rectification of leakage etc
B73: a) M: 25 Grade (Minimum Cement : 340 kg/M3)
B74: 1. In foundations and up to plinths (FFL) at all depths: | D74: CUM | E74: 5750 | F74: =E74*C74 -> 0
B75: i) From FFL up to + 5.5 M lvl. | D75: CUM | E75: 6650
B76: ii) Above + 5.5M lvl up to + 11.0 M lvl | D76: CUM | E76: 6850
B77: ii) Above + 11.0M lvl up to + 16.5M lvl | D77: CUM | E77: 7250
A78: B-03 | B78: For addition of approved quality plasticiser as directed and specified by the engineer incharge (BASF or SIKA make only)
B79: a) For early de shuttering (basic rate:90 Rs/Ltr.) | D79: LTRS | E79: 175 | F79: =E79*C79 -> 0
A80: B-04 | B80: Providing, fabricating, laying and fixing in position reinforcement for all type of RCC works at all levels, including cost of straightening, cutting, bending to required shape, binding with 16 gauge MS annealed binding wire, spacer blocks of cement mortar 1:2 with embedded binding wire of appropriate length, etc. complete as per drawings and specifications [Chairs, pins will not be measured and paid extra. Only authorized laps shall be measured and paid for] Note:- HYSD reinforcements (Fe500) of make "HY-TUF" , "Electro therm" or "ISPAT"
B81: a) High yield strength deformed bars | C81: 4 | D81: MT | E81: 69500 | F81: =E81*C81 -> 278000
A82: B-05 | B82: Providing and fixing form work including necessary centering for footings, columns, pedestals, rafts, blocks, walls, beams, slabs, copings, pipe supports, equipment foundations, floors, roads, water retaining structures / any type of structural members etc. of any shapes including strutting, bracing, shoring, propping, staging, etc. keeping the same in position during concreting and removal of the same after a specified period, including smooth rendering of concrete surface if required, complete as per drawings and specifications (Rate to include coating formwork with approved quality of non-staining mineral oil).
B83: 1. In foundations and up to plinths (FFL) at all depths: | C83: 105 | D83: SQM | E83: 550 | F83: =C83*E83 -> 57750
B84: i) From FFL up to + 5.5 M lvl. | D84: SQM | E84: 625 | F84: =C84*E84 -> 0
A85: B-06 | B85: Providing and fixing plywood form work including necessary centering for alignment and levels for columns, blocks, pedestals, lintels, beams (regular and inverted), slabs, chajjas, copings, gutters, pardi, facias, fins, bands, walls, staircases, slopping RCC elements, rain water chutes, etc. of rectangular, square shapes, curve, including strutting, shoring, bracing, propping, staging, water retaining structure / any type of structure member, etc. keeping the same in position during the concreting and removal of the same after a specified period, etc. complete as per drawings and specifications. The framework shall ensure smooth finish surface without any additional rendering. Rate to include coating formwork with approved quality of non-staining mineral oil.
B86: 1. In foundations and up to plinths (FFL) at all depths: | D86: SQM | E86: 575
B87: i) From FFL up to + 5.5 M lvl. | D87: SQM | E87: 650 | F87: =E87*C87 -> 0
B88: ii) Above + 5.5M lvl up to + 11.0 M lvl | D88: SQM | E88: 725
B89: ii) Above + 11.0 M lvl up to + 16.5 M lvl | D89: SQM | E89: 850
A90: B-08 | B90: Providing free flow grouting under base plates and in pockets for holding down in pockets with GP2 of approved make including formwork, finishing, curing, etc. complete as directed by the Engineer. | D90: CUM | E90: 52500 | F90: =E90*C90 -> 0
A91: B-09 | B91: Providing and doing welding continuous or intermittent using 4.2mm welding rod in line & removing slag etc. complete.(only welding length shall be considered for mesurment.) | D91: RMT | E91: 550
A92: B-11 | B92: Providing and fixing in position in PCC/RCC work at all levels, shuttering for pockets of varying sizes as per details with necessary form work including type of form work where required and carefully removing the same for anchor and holding down bolts for columns, pedestals, pipe rack, equipment foundations, etc. all as per detailed drawing / as directed by the Engineer.
B93: a) For pocket area up to 0.01 Sq.m. and depth up to 0.30M | D93: Nos. | E93: 800 | F93: =E93*C93 -> 0
B94: b) For pocket area above 0.01 Sq.m. up to 0.03 Sq.m. and depth up to 0.30M | D94: Nos. | E94: 1050 | F94: =E94*C94 -> 0
B95: c) For pocket area above 0.03 Sq.m. up to 0.05 Sq.m. and depth up to 0.60M | D95: Nos. | E95: 1250 | F95: =E95*C95 -> 0
B96: d) For pocket area up to 0.01 Sq.m. and depth up to 0.75M | D96: Nos. | E96: 1250 | F96: =E96*C96 -> 0
B97: e) For pocket area above 0.01 Sq.m. up to 0.03 Sq.m. and depth up to 0.75M | D97: Nos. | E97: 1350 | F97: =E97*C97 -> 0
B98: f) For pocket area above 0.03 Sq.m. up to 0.05 Sq.m. and depth up to 1.0M | D98: Nos. | E98: 2000 | F98: =E98*C98 -> 0
B99: g) For pocket area up to 0.01 Sq.m. and depth up to 1.25M | D99: Nos. | E99: 1950 | F99: =E99*C99 -> 0
B100: h) For pocket area above 0.01 Sq.m. up to 0.03 Sq.m. and depth up to 1.25M | D100: Nos. | E100: 2250 | F100: =E100*C100 -> 0
...

Sheet BOQ -U.G TANK WITH PUMP ROOM 
B1: ESTIMATED BOQ FOR PROPOSED U.G TANK WITH PUMP ROOM CIVIL & STRUCTURAL WORKS For SUYOG ELECTRICAL LTD. NO 245/33/B,245/55/B/2,MOJE BODIDARA, TA.VADODARA, GUJARAT, INDIA.
A2: Followings are the scope of work: - 2 LAKH LITTRE +1 LAKH LITTRE WITH MC ROOM Civil and Structural works (Excluding PEB shed) - Approximately 72 SQM TANK + 40 SQM PUMP ROOM -
A3: BOQ
A4: Sr. No. | B4: Description | C4: QTY. | D4: UNIT | E4: RATE | F4: AMOUNT
B5: SECTION- A EARTH WORK AND SOLING
A6: A-01 | B6: Cleaning the area by grass cutting, removing vegetations,roots of trees if any, scraping the existing surfaces up to 150mm, removal of all loose materials and other matters, etc. and disposing off the debris beyond the plant boundary as directed by the Engineer. | C6: 76 | D6: SQ.M. | E6: 35 | F6: =E6*C6 -> 2660
A7: A-01A | B7: Clearing the area by jungle cutting, removing trees / bushes if any from roots, scraping the existing surfaces up to 150mm, removal of all loose materials and other matters, etc. and disposing off the debris beyond the plant boundary as directed by EIC. | D7: SQ.M. | E7: 25 | F7: =E7*C7 -> 0
A8: A-02 | B8: Earth work excavation for all type of work in all soils like black cotton soil, clay, sand, soft and hard murrum, etc. but other than soft and hard rock including shoring, strutting and dewatering due to any sub soil water, rain water or any reason if required and refilling in foundations with selected excavated earth in 350mm layers, watering and consolidating to 250mm thickness, disposing off surplus excavated materials within the plant boundary at selected places, spreading evenly, leveling, etc. complete as per specifications and as directed. (Payment shall be made for 300mm from R.C.C. face for foundations and 200mm from R.C.C. face for GB)
B9: a) From average ground level up to 1.50M depth. | C9: 131 | D9: CUM | E9: 250 | F9: =E9*C9 -> 32750
B10: b) Below 1.5M up to 3M depth | C10: 131 | D10: CUM | E10: 285 | F10: =E10*C10 -> 37335
B11: c) Below 3.0M up to 4.5M depth | C11: 53 | D11: CUM | E11: 350 | F11: =E11*C11 -> 18550
B12: d) Below 4.5M up to 6.0M depth | C12: QRO | D12: CUM | E12: 450
B13: e) Below 6.0M up to 7.5M depth | C13: QRO | D13: CUM | E13: 575
A14: A-03 | B14: Filling in plinth & foundation pits with approved materials including spreading in 150mm layers, watering, ramming, compacting with 10MT vibro/static roller or portable compactor wherever applicable as decided by the Engineer, leveling, etc. complete. (Measurements for compacted volume is considered)
B15: a) With selected earth brought from outside | C15: 16 | D15: CUM | E15: 490 | F15: =E15*C15 -> 7840
B16: b) With approved filling sand brought from Outside. | D16: CUM | E16: 1025 | F16: =E16*C16 -> 0
B17: c) Approved quarry dust filling | D17: CUM | E17: 1150
A18: A-04 | B18: Disposing off surplus excavated materials by carting away, outside of company premises at location decided by contractor and shall be responsibility of contractor | D18: CUM | E18: 150 | F18: =E18*C18 -> 0
A19: A-04A | B19: Disposing off dumped Earth / Debris by carting away, outside of company premises at location decided by contractor and shall be responsibility of contractor
B20: a) Measurement of available material by volume | D20: CUM | E20: 100 | F20: =E20*C20 -> 0
B21: b) Measurement of available material by Dumper | D21: Nos. | E21: 3500
A22: A-05 | B22: Providing and laying black trap rubble soling at required level and grade in foundations, in plinth, ramps, etc. including hand packing, filling interstices with quarry / sand, watering and compacting with suitable vibro roller/ Static roller or earth compactor wherever applicable as decided by the Engineer to the consolidated thickness as stated below:
B23: i) 230mm thick Soling | D23: SQ.M | E23: 517
B24: ii) 150mm thick compacted layer metal packing using 63-90 mm size hand broken stone etc. as directed Engineer in charge/consultant. | C24: 79 | D24: SQ.M | E24: 310 | F24: =E24*C24 -> 24490
B25: iii) 75mm thick compacted layer metal packing using 40-63 mm size hand broken stone etc. as directed Engineer in charge/consultant. | C25: 79 | D25: SQ.M | E25: 150 | F25: =E25*C25 -> 11850
A26: A-06 | B26: Auguring(Upto 8m depth) of under ream pile foundation work in all sorts of soil viz. sand, clay, soft & hard murrum for execution of the above work. Contractor has to brought all necessary tools, tackles, equipments, manpower & supervision. Items also include carting of debris/soil, unloading, stacking, use of bentonite, spreading, levelling, compacting, consolidating surplus marterial within company premises, dewatering & one bulb as per design etc. complete as directed
B27: (a) For 250mm dia. Pile | D27: RM | E27: 300
B28: (b) For 300mm dia. Pile | D28: RM | E28: 350 | F28: =E28*C28 -> 0
B29: (c) For 350mm dia. Pile | D29: RM | E29: 425 | F29: =E29*C29 -> 0
B30: (d) For 400mm dia. Pile | D30: RM | E30: 495 | F30: =E30*C30 -> 0
A31: A-07 | B31: -do- as per item no. A-06 but for construction of extra bulb in the pile at any level. The size of the bulb will be as per design.
B32: (a) For 250mm dia. Pile | D32: NO | E32: 300
B33: (b) For 300mm dia. Pile | D33: NO | E33: 400
B34: (c) For 350mm dia. Pile | D34: NO | E34: 450
B35: (d) For 400mm dia. Pile | D35: NO | E35: 500
B36: TOTAL OF SECTION `A` | F36: =SUM(F6:F35) -> 135475
B37: SECTION - B CONCRETE
A38: B-01 | B38: Providing and laying Plain cement concrete below all R.C.C. member, floors, ramps, chembers etc. with 20mm nominal size graded stone aggregates of approved quality (black trap only) including leveling, compacting, curing and form work if any, etc. complete.
B39: a) Mix 1: 4: 8 | C39: 8 | D39: CUM | E39: 4100 | F39: =E39*C39 -> 32800
B40: b) Mix 1: 3: 6 | D40: CUM | E40: 4175 | F40: =E40*C40 -> 0
A41: B-02 | B41: Providing and laying reinforced cement concrete with 20mm and down size graded stone aggregates in all types of concrete works such as footings, columns, pedestals, rafts, beams, lofts, slabs, walls, lintels, chajjas, canopies, facias, fins, bands, shelves, staircases, all other any type of structural members, pits, chambers, rain water chutes, gutters, pardi, curbs, pipe racks, & equipment foundations, etc. of square, rectangular, hexagonal, octagonal and circular shapes including leaving pockets, vatas, openings in slabs, including vibrating, tamping, finishing, curing and rendering if required, etc. complete as per drawings and specifications but excluding the cost of formwork and reinforcement. (No false staging shall be given.) Cement Make: Ultratech / JK Lakshmi / Ambuja - OPC 53 grade (Applicable to all items)
B42: a) M : 20 Grade (Min. Cement - 300 KG/M3)
B43: 1. In foundations and up to plinths (FFL) at all depths: | D43: CUM | E43: 5450
B44: i) From FFL up to + 5.5 M lvl. | D44: CUM | E44: 5950
B45: b) M: 25 Grade (Min. Cement - 340 KG/M3)
B46: 1. In foundations and up to plinths (FFL) at all depths: | C46: 79 | D46: CUM | E46: 5850 | F46: =E46*C46 -> 462150
B47: i) From FFL up to + 5.0 M lvl. | C47: 5 | D47: CUM | E47: 6175 | F47: =E47*C47 -> 30875
B48: ii) Above + 5.0M lvl up to + 11.0 M lvl | D48: CUM | E48: 6350
B49: c) Extra for M30 Concrete in place of M25 (Min. Cement- 370 KG/M3) | D49: CUM | E49: 950
A50: B-02A | B50: Ready Mix Concreate (Prior Permission shall be taken before using Ready Mix Concrete from engineer Incharge)
B51: Providing and laying ready mix concrete with 20mm and down size graded stone aggregates Without flyash in all types of concrete works such as footings, columns, pedestals, rafts, beams, lofts, slabs, walls, lintels, chajjas, canopies, facias, fins, bands, shelves, staircases, pits, chambers, rain water chutes, gutt­ers, pardi, curbs, pipe racks, & equipment foundations, etc. of square, rectangular, hexagonal, octagonal and circular shapes including leaving pockets, openings in slabs, vibrating, tamping, finishing, curing and rendering if required, etc. complete as per drawings and specifications but excluding the cost of formwork and reinforcement. Cement: OPC53 grade Ultra tech, Ambuja Supply of cement will be in contractor's scope. Mix Design has to be approved from Consultant.
A52: B-02 A1 | B52: In foundations and up to plinths (FFL) at all depths:
B53: a) M: 20 Grade (min . Cement : 300 kg/m3) | D53: Cu.m | E53: 5450
B54: b) M: 25 Grade (min . Cement : 340 kg/m3) | D54: Cu.m | E54: 5850 | F54: =E54*C54 -> 0
B55: c) Extra for M30 Concrete in place of M25 (Min. Cement- 370 KG/M3) | D55: Cu.m | E55: 950
A56: B-02 A2 | B56: In superstructure above finished floor level at all heights.
B57: a) M : 20 Grade
B58: i) From FFL up to + 5.5M lvl. | D58: Cu.m | E58: 5700 | F58: =E58*C58 -> 0
B59: ii) Above + 5.5M lvl. | D59: Cu.m
B60: b) M : 25 Grade
B61: i) From FFL up to + 5.5M lvl. | D61: Cu.m | E61: 5900 | F61: =E61*C61 -> 0
B62: ii) Above + 5.5M lvl up to + 11.0M lvl | D62: Cu.m | E62: 6650
B63: c) Extra for M30 Concrete in place of M25 (Min. Cement- 370 KG/M3) | D63: Cu.m | E63: 950
A64: B-02B | B64: Providing and laying reinforced cement concrete with 20mm and down size graded stone aggregates in PILE. of circular shapes including tamping, curing and development of pile- including use of trimi, breaking (Upto 0.60m length), cleanning etc. complete as per drawings and specifications but excluding the cost of formwork and reinforcement. (USE GRADE OF CONC. M25)
B65: (a) For 250mm dia. Pile | D65: CUM | E65: 5600
B66: (b) For 300mm dia. Pile | D66: CUM | E66: 5369 | F66: =E66*C66 -> 0
B67: (b) For 350mm dia. Pile | D67: CUM | E67: 5650 | F67: =E67*C67 -> 0
B68: (c) For 400mm dia. Pile | D68: CUM | E68: 5650 | F68: =E68*C68 -> 0
A69: B-02C | B69: Providing and laying reinforced cement concrete with 20mm and down size graded stone aggregates in PRECAST concrete works for storm water trench, Chamber Cover etc. of square, rectangular, hexagonal, octagonal and circular shapes including leaving pockets, openings in covers, vibrating, tamping, finishing, curing and rendering if required, etc. complete as per drawings and specifications. The rate includes the cost of formwork and installing the elements in line and level. (Reinforcement steel is paid seperately in item no. B-05 )
B70: (a) M25 grade | D70: CUM | E70: 9500
B71: (b) M30 grade | D71: CUM | E71: 9500
A72: B-02D | B72: Providing and laying M25 Grade Reinforced cement concrete for water retaining structures/Cable Trech / basement structures/over head tanks, ETP, scale pit, basins sumps / sump pits, manholes, inspection chambers of sewage / drainage lines etc at any level and location. Including addition of water proofing compound WAREP 1000L Manufactured by Thermax Ltd. , FOSROC-CONPLAST '-X4211C- or equivalent approved make in concrete as per approved manufacturer's specification, including pressure cement grouting of mix 1:1 with water proofing additives MAXGROUT 100 MANUFACTURED by THERMAX LTD.or equivalent at construction joints, weak spot / honey combs and testing the same for water tightness as per requirements of IS 3370 and making good defects / leakages as instructed by Engineers / Owners. Rate also to include cost of water proofing compound, testing and rectification of leakage etc
B73: a) M: 25 Grade (Minimum Cement : 340 kg/M3)
B74: 1. In foundations and up to plinths (FFL) at all depths: | D74: CUM | E74: 5750 | F74: =E74*C74 -> 0
B75: i) From FFL up to + 5.5 M lvl. | D75: CUM | E75: 6650
B76: ii) Above + 5.5M lvl up to + 11.0 M lvl | D76: CUM | E76: 6850
B77: ii) Above + 11.0M lvl up to + 16.5M lvl | D77: CUM | E77: 7250
A78: B-03 | B78: For addition of approved quality plasticiser as directed and specified by the engineer incharge (BASF or SIKA make only)
B79: a) For early de shuttering (basic rate:90 Rs/Ltr.) | D79: LTRS | E79: 175 | F79: =E79*C79 -> 0
A80: B-04 | B80: Providing, fabricating, laying and fixing in position reinforcement for all type of RCC works at all levels, including cost of straightening, cutting, bending to required shape, binding with 16 gauge MS annealed binding wire, spacer blocks of cement mortar 1:2 with embedded binding wire of appropriate length, etc. complete as per drawings and specifications [Chairs, pins will not be measured and paid extra. Only authorized laps shall be measured and paid for] Note:- HYSD reinforcements (Fe500) of make "HY-TUF" , "Electro therm" or "ISPAT"
B81: a) High yield strength deformed bars | C81: 13 | D81: MT | E81: 69500 | F81: =E81*C81 -> 903500
A82: B-05 | B82: Providing and fixing form work including necessary centering for footings, columns, pedestals, rafts, blocks, walls, beams, slabs, copings, pipe supports, equipment foundations, floors, roads, water retaining structures / any type of structural members etc. of any shapes including strutting, bracing, shoring, propping, staging, etc. keeping the same in position during concreting and removal of the same after a specified period, including smooth rendering of concrete surface if required, complete as per drawings and specifications (Rate to include coating formwork with approved quality of non-staining mineral oil).
B83: 1. In foundations and up to plinths (FFL) at all depths: | C83: 405 | D83: SQM | E83: 550 | F83: =C83*E83 -> 222750
B84: i) From FFL up to + 5.5 M lvl. | D84: SQM | E84: 625 | F84: =C84*E84 -> 0
A85: B-06 | B85: Providing and fixing plywood form work including necessary centering for alignment and levels for columns, blocks, pedestals, lintels, beams (regular and inverted), slabs, chajjas, copings, gutters, pardi, facias, fins, bands, walls, staircases, slopping RCC elements, rain water chutes, etc. of rectangular, square shapes, curve, including strutting, shoring, bracing, propping, staging, water retaining structure / any type of structure member, etc. keeping the same in position during the concreting and removal of the same after a specified period, etc. complete as per drawings and specifications. The framework shall ensure smooth finish surface without any additional rendering. Rate to include coating formwork with approved quality of non-staining mineral oil.
B86: 1. In foundations and up to plinths (FFL) at all depths: | D86: SQM | E86: 575
B87: i) From FFL up to + 5.5 M lvl. | C87: 42 | D87: SQM | E87: 650 | F87: =E87*C87 -> 27300
B88: ii) Above + 5.5M lvl up to + 11.0 M lvl | D88: SQM | E88: 725
B89: ii) Above + 11.0 M lvl up to + 16.5 M lvl | D89: SQM | E89: 850
A90: B-08 | B90: Providing free flow grouting under base plates and in pockets for holding down in pockets with GP2 of approved make including formwork, finishing, curing, etc. complete as directed by the Engineer. | C90: 0.3 | D90: CUM | E90: 52500 | F90: =E90*C90 -> 15750
A91: B-09 | B91: Providing and doing welding continuous or intermittent using 4.2mm welding rod in line & removing slag etc. complete.(only welding length shall be considered for mesurment.) | D91: RMT | E91: 550
A92: B-11 | B92: Providing and fixing in position in PCC/RCC work at all levels, shuttering for pockets of varying sizes as per details with necessary form work including type of form work where required and carefully removing the same for anchor and holding down bolts for columns, pedestals, pipe rack, equipment foundations, etc. all as per detailed drawing / as directed by the Engineer.
B93: a) For pocket area up to 0.01 Sq.m. and depth up to 0.30M | D93: Nos. | E93: 800 | F93: =E93*C93 -> 0
B94: b) For pocket area above 0.01 Sq.m. up to 0.03 Sq.m. and depth up to 0.30M | D94: Nos. | E94: 1050 | F94: =E94*C94 -> 0
B95: c) For pocket area above 0.03 Sq.m. up to 0.05 Sq.m. and depth up to 0.60M | D95: Nos. | E95: 1250 | F95: =E95*C95 -> 0
B96: d) For pocket area up to 0.01 Sq.m. and depth up to 0.75M | D96: Nos. | E96: 1250 | F96: =E96*C96 -> 0
B97: e) For pocket area above 0.01 Sq.m. up to 0.03 Sq.m. and depth up to 0.75M | D97: Nos. | E97: 1350 | F97: =E97*C97 -> 0
B98: f) For pocket area above 0.03 Sq.m. up to 0.05 Sq.m. and depth up to 1.0M | D98: Nos. | E98: 2000 | F98: =E98*C98 -> 0
B99: g) For pocket area up to 0.01 Sq.m. and depth up to 1.25M | D99: Nos. | E99: 1950 | F99: =E99*C99 -> 0
B100: h) For pocket area above 0.01 Sq.m. up to 0.03 Sq.m. and depth up to 1.25M | D100: Nos. | E100: 2250 | F100: =E100*C100 -> 0
...

Sheet BOQ -ENTRANCE GATE 
B1: ESTIMATED BOQ FOR PROPOSED WEIGH BRIDGE CIVIL & STRUCTURAL WORKS For SUYOG ELECTRICAL LTD. NO 245/33/B,245/55/B/2,MOJE BODIDARA, TA.VADODARA, GUJARAT, INDIA.
A2: Followings are the scope of work: - 9.0 M WIDE GATE - | I2: GATE AREA
A3: BOQ
A4: Sr. No. | B4: Description | C4: QTY. | D4: UNIT | E4: RATE | F4: AMOUNT
B5: SECTION- A EARTH WORK AND SOLING
A6: A-01 | B6: Cleaning the area by grass cutting, removing vegetations,roots of trees if any, scraping the existing surfaces up to 150mm, removal of all loose materials and other matters, etc. and disposing off the debris beyond the plant boundary as directed by the Engineer. | C6: 140 | D6: SQ.M. | E6: 35 | F6: =E6*C6 -> 4900
A7: A-01A | B7: Clearing the area by jungle cutting, removing trees / bushes if any from roots, scraping the existing surfaces up to 150mm, removal of all loose materials and other matters, etc. and disposing off the debris beyond the plant boundary as directed by EIC. | D7: SQ.M. | E7: 25 | F7: =E7*C7 -> 0
A8: A-02 | B8: Earth work excavation for all type of work in all soils like black cotton soil, clay, sand, soft and hard murrum, etc. but other than soft and hard rock including shoring, strutting and dewatering due to any sub soil water, rain water or any reason if required and refilling in foundations with selected excavated earth in 350mm layers, watering and consolidating to 250mm thickness, disposing off surplus excavated materials within the plant boundary at selected places, spreading evenly, leveling, etc. complete as per specifications and as directed. (Payment shall be made for 300mm from R.C.C. face for foundations and 200mm from R.C.C. face for GB)
B9: a) From average ground level up to 1.50M depth. | C9: 27 | D9: CUM | E9: 250 | F9: =E9*C9 -> 6750
B10: b) Below 1.5M up to 3M depth | D10: CUM | E10: 285 | F10: =E10*C10 -> 0
B11: c) Below 3.0M up to 4.5M depth | D11: CUM | E11: 350 | F11: =E11*C11 -> 0
B12: d) Below 4.5M up to 6.0M depth | D12: CUM | E12: 450
B13: e) Below 6.0M up to 7.5M depth | D13: CUM | E13: 575
A14: A-03 | B14: Filling in plinth & foundation pits with approved materials including spreading in 150mm layers, watering, ramming, compacting with 10MT vibro/static roller or portable compactor wherever applicable as decided by the Engineer, leveling, etc. complete. (Measurements for compacted volume is considered)
B15: a) With selected earth brought from outside | C15: 3 | D15: CUM | E15: 490 | F15: =E15*C15 -> 1470
B16: b) With approved filling sand brought from Outside. | C16: 2 | D16: CUM | E16: 1025 | F16: =E16*C16 -> 2050
B17: c) Approved quarry dust filling | D17: CUM | E17: 1150
A18: A-04 | B18: Disposing off surplus excavated materials by carting away, outside of company premises at location decided by contractor and shall be responsibility of contractor | C18: 17 | D18: CUM | E18: 150 | F18: =E18*C18 -> 2550
A19: A-04A | B19: Disposing off dumped Earth / Debris by carting away, outside of company premises at location decided by contractor and shall be responsibility of contractor
B20: a) Measurement of available material by volume | D20: CUM | E20: 100 | F20: =E20*C20 -> 0
B21: b) Measurement of available material by Dumper | D21: Nos. | E21: 3500
A22: A-05 | B22: Providing and laying black trap rubble soling at required level and grade in foundations, in plinth, ramps, etc. including hand packing, filling interstices with quarry / sand, watering and compacting with suitable vibro roller/ Static roller or earth compactor wherever applicable as decided by the Engineer to the consolidated thickness as stated below:
B23: i) 230mm thick Soling | D23: SQ.M | E23: 517
B24: ii) 150mm thick compacted layer metal packing using 63-90 mm size hand broken stone etc. as directed Engineer in charge/consultant. | C24: 13 | D24: SQ.M | E24: 310 | F24: =E24*C24 -> 4030
B25: iii) 75mm thick compacted layer metal packing using 40-63 mm size hand broken stone etc. as directed Engineer in charge/consultant. | D25: SQ.M | E25: 150 | F25: =E25*C25 -> 0
A26: A-06 | B26: Auguring(Upto 8m depth) of under ream pile foundation work in all sorts of soil viz. sand, clay, soft & hard murrum for execution of the above work. Contractor has to brought all necessary tools, tackles, equipments, manpower & supervision. Items also include carting of debris/soil, unloading, stacking, use of bentonite, spreading, levelling, compacting, consolidating surplus marterial within company premises, dewatering & one bulb as per design etc. complete as directed
B27: (a) For 250mm dia. Pile | D27: RM | E27: 300
B28: (b) For 300mm dia. Pile | D28: RM | E28: 350 | F28: =E28*C28 -> 0
B29: (c) For 350mm dia. Pile | C29: 84 | D29: RM | E29: 425 | F29: =E29*C29 -> 35700
B30: (d) For 400mm dia. Pile | D30: RM | E30: 495 | F30: =E30*C30 -> 0
A31: A-07 | B31: -do- as per item no. A-06 but for construction of extra bulb in the pile at any level. The size of the bulb will be as per design.
B32: (a) For 250mm dia. Pile | D32: NO | E32: 300
B33: (b) For 300mm dia. Pile | D33: NO | E33: 400
B34: (c) For 350mm dia. Pile | D34: NO | E34: 450
B35: (d) For 400mm dia. Pile | D35: NO | E35: 500
B36: TOTAL OF SECTION `A` | F36: =SUM(F6:F35) -> 57450
B37: SECTION - B CONCRETE
A38: B-01 | B38: Providing and laying Plain cement concrete below all R.C.C. member, floors, ramps, chembers etc. with 20mm nominal size graded stone aggregates of approved quality (black trap only) including leveling, compacting, curing and form work if any, etc. complete.
B39: a) Mix 1: 4: 8 | C39: 2 | D39: CUM | E39: 4100 | F39: =E39*C39 -> 8200
B40: b) Mix 1: 3: 6 | D40: CUM | E40: 4175 | F40: =E40*C40 -> 0
A41: B-02 | B41: Providing and laying reinforced cement concrete with 20mm and down size graded stone aggregates in all types of concrete works such as footings, columns, pedestals, rafts, beams, lofts, slabs, walls, lintels, chajjas, canopies, facias, fins, bands, shelves, staircases, all other any type of structural members, pits, chambers, rain water chutes, gutters, pardi, curbs, pipe racks, & equipment foundations, etc. of square, rectangular, hexagonal, octagonal and circular shapes including leaving pockets, vatas, openings in slabs, including vibrating, tamping, finishing, curing and rendering if required, etc. complete as per drawings and specifications but excluding the cost of formwork and reinforcement. (No false staging shall be given.) Cement Make: Ultratech / JK Lakshmi / Ambuja - OPC 53 grade (Applicable to all items)
B42: a) M : 20 Grade (Min. Cement - 300 KG/M3)
B43: 1. In foundations and up to plinths (FFL) at all depths: | D43: CUM | E43: 5450
B44: i) From FFL up to + 5.5 M lvl. | D44: CUM | E44: 5950
B45: b) M: 25 Grade (Min. Cement - 340 KG/M3)
B46: 1. In foundations and up to plinths (FFL) at all depths: | C46: 13 | D46: CUM | E46: 5850 | F46: =E46*C46 -> 76050
B47: i) From FFL up to + 5.0 M lvl. | C47: 28 | D47: CUM | E47: 6175 | F47: =E47*C47 -> 172900
B48: ii) Above + 5.0M lvl up to + 11.0 M lvl | D48: CUM | E48: 6350
B49: c) Extra for M30 Concrete in place of M25 (Min. Cement- 370 KG/M3) | D49: CUM | E49: 950
A50: B-02A | B50: Ready Mix Concreate (Prior Permission shall be taken before using Ready Mix Concrete from engineer Incharge)
B51: Providing and laying ready mix concrete with 20mm and down size graded stone aggregates Without flyash in all types of concrete works such as footings, columns, pedestals, rafts, beams, lofts, slabs, walls, lintels, chajjas, canopies, facias, fins, bands, shelves, staircases, pits, chambers, rain water chutes, gutt­ers, pardi, curbs, pipe racks, & equipment foundations, etc. of square, rectangular, hexagonal, octagonal and circular shapes including leaving pockets, openings in slabs, vibrating, tamping, finishing, curing and rendering if required, etc. complete as per drawings and specifications but excluding the cost of formwork and reinforcement. Cement: OPC53 grade Ultra tech, Ambuja Supply of cement will be in contractor's scope. Mix Design has to be approved from Consultant.
A52: B-02 A1 | B52: In foundations and up to plinths (FFL) at all depths:
B53: a) M: 20 Grade (min . Cement : 300 kg/m3) | D53: Cu.m | E53: 5450
B54: b) M: 25 Grade (min . Cement : 340 kg/m3) | D54: Cu.m | E54: 5850 | F54: =E54*C54 -> 0
B55: c) Extra for M30 Concrete in place of M25 (Min. Cement- 370 KG/M3) | D55: Cu.m | E55: 950
A56: B-02 A2 | B56: In superstructure above finished floor level at all heights.
B57: a) M : 20 Grade
B58: i) From FFL up to + 5.5M lvl. | D58: Cu.m | E58: 5700 | F58: =E58*C58 -> 0
B59: ii) Above + 5.5M lvl. | D59: Cu.m
B60: b) M : 25 Grade
B61: i) From FFL up to + 5.5M lvl. | D61: Cu.m | E61: 5900 | F61: =E61*C61 -> 0
B62: ii) Above + 5.5M lvl up to + 11.0M lvl | D62: Cu.m | E62: 6650
B63: c) Extra for M30 Concrete in place of M25 (Min. Cement- 370 KG/M3) | D63: Cu.m | E63: 950
A64: B-02B | B64: Providing and laying reinforced cement concrete with 20mm and down size graded stone aggregates in PILE. of circular shapes including tamping, curing and development of pile- including use of trimi, breaking (Upto 0.60m length), cleanning etc. complete as per drawings and specifications but excluding the cost of formwork and reinforcement. (USE GRADE OF CONC. M25)
B65: (a) For 250mm dia. Pile | D65: CUM | E65: 5600
B66: (b) For 300mm dia. Pile | D66: CUM | E66: 5369 | F66: =E66*C66 -> 0
B67: (b) For 350mm dia. Pile | D67: CUM | E67: 5650 | F67: =E67*C67 -> 0
B68: (c) For 400mm dia. Pile | D68: CUM | E68: 5650 | F68: =E68*C68 -> 0
A69: B-02C | B69: Providing and laying reinforced cement concrete with 20mm and down size graded stone aggregates in PRECAST concrete works for storm water trench, Chamber Cover etc. of square, rectangular, hexagonal, octagonal and circular shapes including leaving pockets, openings in covers, vibrating, tamping, finishing, curing and rendering if required, etc. complete as per drawings and specifications. The rate includes the cost of formwork and installing the elements in line and level. (Reinforcement steel is paid seperately in item no. B-05 )
B70: (a) M25 grade | D70: CUM | E70: 9500
B71: (b) M30 grade | D71: CUM | E71: 9500
A72: B-02D | B72: Providing and laying M25 Grade Reinforced cement concrete for water retaining structures/Cable Trech / basement structures/over head tanks, ETP, scale pit, basins sumps / sump pits, manholes, inspection chambers of sewage / drainage lines etc at any level and location. Including addition of water proofing compound WAREP 1000L Manufactured by Thermax Ltd. , FOSROC-CONPLAST '-X4211C- or equivalent approved make in concrete as per approved manufacturer's specification, including pressure cement grouting of mix 1:1 with water proofing additives MAXGROUT 100 MANUFACTURED by THERMAX LTD.or equivalent at construction joints, weak spot / honey combs and testing the same for water tightness as per requirements of IS 3370 and making good defects / leakages as instructed by Engineers / Owners. Rate also to include cost of water proofing compound, testing and rectification of leakage etc
B73: a) M: 25 Grade (Minimum Cement : 340 kg/M3)
B74: 1. In foundations and up to plinths (FFL) at all depths: | D74: CUM | E74: 5750 | F74: =E74*C74 -> 0
B75: i) From FFL up to + 5.5 M lvl. | D75: CUM | E75: 6650
B76: ii) Above + 5.5M lvl up to + 11.0 M lvl | D76: CUM | E76: 6850
B77: ii) Above + 11.0M lvl up to + 16.5M lvl | D77: CUM | E77: 7250
A78: B-03 | B78: For addition of approved quality plasticiser as directed and specified by the engineer incharge (BASF or SIKA make only)
B79: a) For early de shuttering (basic rate:90 Rs/Ltr.) | D79: LTRS | E79: 175 | F79: =E79*C79 -> 0
A80: B-04 | B80: Providing, fabricating, laying and fixing in position reinforcement for all type of RCC works at all levels, including cost of straightening, cutting, bending to required shape, binding with 16 gauge MS annealed binding wire, spacer blocks of cement mortar 1:2 with embedded binding wire of appropriate length, etc. complete as per drawings and specifications [Chairs, pins will not be measured and paid extra. Only authorized laps shall be measured and paid for] Note:- HYSD reinforcements (Fe500) of make "HY-TUF" , "Electro therm" or "ISPAT"
B81: a) High yield strength deformed bars | C81: 6 | D81: MT | E81: 69500 | F81: =E81*C81 -> 417000
A82: B-05 | B82: Providing and fixing form work including necessary centering for footings, columns, pedestals, rafts, blocks, walls, beams, slabs, copings, pipe supports, equipment foundations, floors, roads, water retaining structures / any type of structural members etc. of any shapes including strutting, bracing, shoring, propping, staging, etc. keeping the same in position during concreting and removal of the same after a specified period, including smooth rendering of concrete surface if required, complete as per drawings and specifications (Rate to include coating formwork with approved quality of non-staining mineral oil).
B83: 1. In foundations and up to plinths (FFL) at all depths: | D83: SQM | E83: 550 | F83: =C83*E83 -> 0
B84: i) From FFL up to + 5.5 M lvl. | D84: SQM | E84: 625 | F84: =C84*E84 -> 0
A85: B-06 | B85: Providing and fixing plywood form work including necessary centering for alignment and levels for columns, blocks, pedestals, lintels, beams (regular and inverted), slabs, chajjas, copings, gutters, pardi, facias, fins, bands, walls, staircases, slopping RCC elements, rain water chutes, etc. of rectangular, square shapes, curve, including strutting, shoring, bracing, propping, staging, water retaining structure / any type of structure member, etc. keeping the same in position during the concreting and removal of the same after a specified period, etc. complete as per drawings and specifications. The framework shall ensure smooth finish surface without any additional rendering. Rate to include coating formwork with approved quality of non-staining mineral oil.
B86: 1. In foundations and up to plinths (FFL) at all depths: | C86: 70 | D86: SQM | E86: 575 | F86: =C86*E86 -> 40250
B87: i) From FFL up to + 5.5 M lvl. | C87: 236 | D87: SQM | E87: 650 | F87: =E87*C87 -> 153400
B88: ii) Above + 5.5M lvl up to + 11.0 M lvl | D88: SQM | E88: 725
B89: ii) Above + 11.0 M lvl up to + 16.5 M lvl | D89: SQM | E89: 850
A90: B-08 | B90: Providing free flow grouting under base plates and in pockets for holding down in pockets with GP2 of approved make including formwork, finishing, curing, etc. complete as directed by the Engineer. | C90: 0.1 | D90: CUM | E90: 52500 | F90: =E90*C90 -> 5250
A91: B-09 | B91: Providing and doing welding continuous or intermittent using 4.2mm welding rod in line & removing slag etc. complete.(only welding length shall be considered for mesurment.) | D91: RMT | E91: 550
A92: B-11 | B92: Providing and fixing in position in PCC/RCC work at all levels, shuttering for pockets of varying sizes as per details with necessary form work including type of form work where required and carefully removing the same for anchor and holding down bolts for columns, pedestals, pipe rack, equipment foundations, etc. all as per detailed drawing / as directed by the Engineer.
B93: a) For pocket area up to 0.01 Sq.m. and depth up to 0.30M | D93: Nos. | E93: 800 | F93: =E93*C93 -> 0
B94: b) For pocket area above 0.01 Sq.m. up to 0.03 Sq.m. and depth up to 0.30M | D94: Nos. | E94: 1050 | F94: =E94*C94 -> 0
B95: c) For pocket area above 0.03 Sq.m. up to 0.05 Sq.m. and depth up to 0.60M | D95: Nos. | E95: 1250 | F95: =E95*C95 -> 0
B96: d) For pocket area up to 0.01 Sq.m. and depth up to 0.75M | D96: Nos. | E96: 1250 | F96: =E96*C96 -> 0
B97: e) For pocket area above 0.01 Sq.m. up to 0.03 Sq.m. and depth up to 0.75M | D97: Nos. | E97: 1350 | F97: =E97*C97 -> 0
B98: f) For pocket area above 0.03 Sq.m. up to 0.05 Sq.m. and depth up to 1.0M | D98: Nos. | E98: 2000 | F98: =E98*C98 -> 0
B99: g) For pocket area up to 0.01 Sq.m. and depth up to 1.25M | D99: Nos. | E99: 1950 | F99: =E99*C99 -> 0
B100: h) For pocket area above 0.01 Sq.m. up to 0.03 Sq.m. and depth up to 1.25M | D100: Nos. | E100: 2250 | F100: =E100*C100 -> 0
...
